begin_compilation
  name " InvalidCompilationID"
  method "InvalidCompilationID"
  date 1743444013667
end_compilation
begin_compilation
  name " sketch-MultiplyLoop-0"
  method "sketch-MultiplyLoop-0"
  date 1743444013736
end_compilation
begin_compilation
  name " InvalidCompilationID"
  method "InvalidCompilationID"
  date 1743444013743
end_compilation
begin_compilation
  name " sketch-MultiplyLoop-0"
  method "sketch-MultiplyLoop-0"
  date 1743444013772
end_compilation
begin_compilation
  name " InvalidCompilationID"
  method "InvalidCompilationID"
  date 1743444013777
end_compilation
begin_compilation
  name " sketch-MultiplyLoop-0"
  method "sketch-MultiplyLoop-0"
  date 1743444013800
end_compilation
begin_cfg
  name "Final HIR schedule"
  begin_block
    name "B0"
    from_bci -1
    to_bci -1
    predecessors 
    successors "B1" 
    xhandlers
    flags 
    probability 4607182418800017408
    begin_IR
      HIR
f <@#|@fixed with next>@ <|@
tid v0 <|@
d <@d|@=== Debug Properties ===
hasSpeculationFence: false
stamp: void
=== Inputs ===
stateAfter: - 
=== Succesors ===
next: v6 
=== Usages ===
=== Predecessor ===
- >@ <|@
instruction <@StartNode|@org.graalvm.compiler.nodes.StartNode>@ stateAfter: - #next: v6  <|@  <|@
f <@~|@floating>@ <|@
tid i5 <|@
d <@d|@=== Debug Properties ===
isDefaultStable: false
nodeSourcePosition: at MatMul.MatMul.MultiplyLoop(MatMul.java:35) [bci: 0]
rawvalue: 0
stableDimension: 0
stamp: i32 [0]
stampKind: i32
value: int[0|0x0]
=== Inputs ===
=== Succesors ===
=== Usages ===
i29 i107 i104 
=== Predecessor ===
- >@ <|@
instruction <@Constant|@org.graalvm.compiler.nodes.ConstantNode>@  <|@  <|@
f <@~|@floating>@ <|@
tid i107 <|@
d <@d|@=== Debug Properties ===
stamp: i32
=== Inputs ===
index: i5 
=== Succesors ===
=== Usages ===
i42 
=== Predecessor ===
- >@ <|@
instruction <@GlobalThreadSize|@uk.ac.manchester.tornado.drivers.opencl.graal.nodes.GlobalThreadSizeNode>@ index: i5  <|@  <|@
f <@~|@floating>@ <|@
tid i39 <|@
d <@d|@=== Debug Properties ===
isDefaultStable: false
nodeSourcePosition: at MatMul.MatMul.MultiplyLoop(MatMul.java:38) [bci: 55]
rawvalue: 1
stableDimension: 0
stamp: i32 [1]
stampKind: i32
value: int[1|0x1]
=== Inputs ===
=== Succesors ===
=== Usages ===
i40 i108 i111 
=== Predecessor ===
- >@ <|@
instruction <@Constant|@org.graalvm.compiler.nodes.ConstantNode>@  <|@  <|@
f <@~|@floating>@ <|@
tid i111 <|@
d <@d|@=== Debug Properties ===
stamp: i32
=== Inputs ===
index: i39 
=== Succesors ===
=== Usages ===
i44 
=== Predecessor ===
- >@ <|@
instruction <@GlobalThreadSize|@uk.ac.manchester.tornado.drivers.opencl.graal.nodes.GlobalThreadSizeNode>@ index: i39  <|@  <|@
f <@~|@floating>@ <|@
tid f25 <|@
d <@d|@=== Debug Properties ===
isDefaultStable: false
nodeSourcePosition: at MatMul.MatMul.MultiplyLoop(MatMul.java:37) [bci: 20]
rawvalue: 0.0
stableDimension: 0
stamp: f32! [0.0]
stampKind: f32
value: float[0.0|0x0]
=== Inputs ===
=== Succesors ===
=== Usages ===
f28 
=== Predecessor ===
- >@ <|@
instruction <@Constant|@org.graalvm.compiler.nodes.ConstantNode>@  <|@  <|@
f <@~|@floating>@ <|@
tid a3 <|@
d <@d|@=== Debug Properties ===
index: 2
stamp: a# uk.ac.manchester.tornado.api.types.matrix.Matrix2DFloat
uncheckedStamp: [null]
=== Inputs ===
=== Succesors ===
=== Usages ===
j102 v150 
=== Predecessor ===
- >@ <|@
instruction <@Parameter|@org.graalvm.compiler.nodes.ParameterNode>@  <|@  <|@
f <@~|@floating>@ <|@
tid j113 <|@
d <@d|@=== Debug Properties ===
isDefaultStable: false
nodeSourcePosition: at uk.ac.manchester.tornado.api.types.matrix.Matrix2DFloat.get(Matrix2DFloat.java:106) [bci: 1]
at MatMul.MatMul.MultiplyLoop(MatMul.java:39) [bci: 40]
rawvalue: 32
stableDimension: 0
stamp: i64 [32]
stampKind: i64
value: long[32|0x20]
=== Inputs ===
=== Succesors ===
=== Usages ===
v148 v149 v150 
=== Predecessor ===
- >@ <|@
instruction <@Constant|@org.graalvm.compiler.nodes.ConstantNode>@  <|@  <|@
f <@~|@floating>@ <|@
tid v150 <|@
d <@d|@=== Debug Properties ===
memoryRegister: uk.ac.manchester.tornado.drivers.opencl.graal.OCLArchitecture$OCLMemoryBase@73393584
stamp: void*
=== Inputs ===
base: a3 
index: j113 
=== Succesors ===
=== Usages ===
a122 
=== Predecessor ===
- >@ <|@
instruction <@OCLAddress|@uk.ac.manchester.tornado.drivers.opencl.graal.lir.OCLAddressNode>@ base: a3 index: j113  <|@  <|@
f <@~|@floating>@ <|@
tid a2 <|@
d <@d|@=== Debug Properties ===
index: 1
stamp: a# uk.ac.manchester.tornado.api.types.matrix.Matrix2DFloat
uncheckedStamp: [null]
=== Inputs ===
=== Succesors ===
=== Usages ===
j101 v149 
=== Predecessor ===
- >@ <|@
instruction <@Parameter|@org.graalvm.compiler.nodes.ParameterNode>@  <|@  <|@
f <@~|@floating>@ <|@
tid v149 <|@
d <@d|@=== Debug Properties ===
memoryRegister: uk.ac.manchester.tornado.drivers.opencl.graal.OCLArchitecture$OCLMemoryBase@73393584
stamp: void*
=== Inputs ===
base: a2 
index: j113 
=== Succesors ===
=== Usages ===
a118 
=== Predecessor ===
- >@ <|@
instruction <@OCLAddress|@uk.ac.manchester.tornado.drivers.opencl.graal.lir.OCLAddressNode>@ base: a2 index: j113  <|@  <|@
f <@~|@floating>@ <|@
tid i95 <|@
d <@d|@=== Debug Properties ===
isDefaultStable: false
nodeSourcePosition: at uk.ac.manchester.tornado.api.types.utils.StorageFormats.toRowMajor(StorageFormats.java:60) [bci: 2]
at uk.ac.manchester.tornado.api.types.matrix.Matrix2DFloat.set(Matrix2DFloat.java:110) [bci: 10]
at MatMul.MatMul.MultiplyLoop(MatMul.java:41) [bci: 67]
rawvalue: 10
stableDimension: 0
stamp: i32 [10]
stampKind: i32
value: int[10|0xa]
=== Inputs ===
=== Succesors ===
=== Usages ===
i96 i97 
=== Predecessor ===
- >@ <|@
instruction <@Constant|@org.graalvm.compiler.nodes.ConstantNode>@  <|@  <|@
f <@~|@floating>@ <|@
tid i87 <|@
d <@d|@=== Debug Properties ===
isDefaultStable: false
rawvalue: 6
stableDimension: 0
stamp: i32 [6]
stampKind: i32
value: int[6|0x6]
=== Inputs ===
=== Succesors ===
=== Usages ===
i137 i140 
=== Predecessor ===
- >@ <|@
instruction <@Constant|@org.graalvm.compiler.nodes.ConstantNode>@  <|@  <|@
f <@~|@floating>@ <|@
tid i59 <|@
d <@d|@=== Debug Properties ===
isDefaultStable: false
nodeSourcePosition: at uk.ac.manchester.tornado.api.types.arrays.FloatArray.set(FloatArray.java:166) [bci: 15]
at uk.ac.manchester.tornado.api.types.matrix.Matrix2DFloat.set(Matrix2DFloat.java:110) [bci: 14]
at MatMul.MatMul.MultiplyLoop(MatMul.java:41) [bci: 67]
rawvalue: 2
stableDimension: 0
stamp: i32 [2]
stampKind: i32
value: int[2|0x2]
=== Inputs ===
=== Succesors ===
=== Usages ===
j60 j74 j86 
=== Predecessor ===
- >@ <|@
instruction <@Constant|@org.graalvm.compiler.nodes.ConstantNode>@  <|@  <|@
f <@~|@floating>@ <|@
tid a1 <|@
d <@d|@=== Debug Properties ===
index: 0
stamp: a# uk.ac.manchester.tornado.api.types.matrix.Matrix2DFloat
uncheckedStamp: [null]
=== Inputs ===
=== Succesors ===
=== Usages ===
j100 v148 
=== Predecessor ===
- >@ <|@
instruction <@Parameter|@org.graalvm.compiler.nodes.ParameterNode>@  <|@  <|@
f <@~|@floating>@ <|@
tid v148 <|@
d <@d|@=== Debug Properties ===
memoryRegister: uk.ac.manchester.tornado.drivers.opencl.graal.OCLArchitecture$OCLMemoryBase@73393584
stamp: void*
=== Inputs ===
base: a1 
index: j113 
=== Succesors ===
=== Usages ===
a115 
=== Predecessor ===
- >@ <|@
instruction <@OCLAddress|@uk.ac.manchester.tornado.drivers.opencl.graal.lir.OCLAddressNode>@ base: a1 index: j113  <|@  <|@
f <@~|@floating>@ <|@
tid i104 <|@
d <@d|@=== Debug Properties ===
stamp: i32
=== Inputs ===
index: i5 
=== Succesors ===
=== Usages ===
i18 
=== Predecessor ===
- >@ <|@
instruction <@GlobalThreadId|@uk.ac.manchester.tornado.drivers.opencl.graal.nodes.GlobalThreadIdNode>@ index: i5  <|@  <|@
f <@~|@floating>@ <|@
tid i108 <|@
d <@d|@=== Debug Properties ===
stamp: i32
=== Inputs ===
index: i39 
=== Succesors ===
=== Usages ===
i8 
=== Predecessor ===
- >@ <|@
instruction <@GlobalThreadId|@uk.ac.manchester.tornado.drivers.opencl.graal.nodes.GlobalThreadIdNode>@ index: i39  <|@  <|@
f <@~|@floating>@ <|@
tid i10 <|@
d <@d|@=== Debug Properties ===
isDefaultStable: false
nodeSourcePosition: at MatMul.MatMul.MultiplyLoop(MatMul.java:35) [bci: 3]
rawvalue: 1024
stableDimension: 0
stamp: i32 [1024]
stampKind: i32
value: int[1024|0x400]
=== Inputs ===
=== Succesors ===
=== Usages ===
v31 v11 v20 
=== Predecessor ===
- >@ <|@
instruction <@Constant|@org.graalvm.compiler.nodes.ConstantNode>@  <|@  <|@
f <@*|@fixed>@ <|@
tid v6 <|@
d <@d|@=== Debug Properties ===
nodeSourcePosition: at MatMul.MatMul.MultiplyLoop(MatMul.java:35) [bci: 2]
stamp: void
=== Inputs ===
=== Succesors ===
=== Usages ===
v7 
=== Predecessor ===
v0 >@ <|@
instruction <@EndNode|@org.graalvm.compiler.nodes.EndNode>@  <|@  <|@
    end_IR
  end_block
  begin_block
    name "B1"
    from_bci -1
    to_bci -1
    predecessors "B0" "B8" 
    successors "B2" "B9" 
    xhandlers
    flags "llh" 
    loop_index 0
    loop_depth 1
    probability 4611686018427387904
    begin_IR
      HIR
f <@~|@floating>@ <|@
tid i8 <|@
d <@d|@=== Debug Properties ===
nodeSourcePosition: at MatMul.MatMul.MultiplyLoop(MatMul.java:35) [bci: 2]
stamp: i32
valueDescription: i32
=== Inputs ===
merge: v7 
values: i108 i44 
=== Succesors ===
=== Usages ===
i44 v11 i96 
=== Predecessor ===
- >@ <|@
instruction <@ValuePhi|@org.graalvm.compiler.nodes.ValuePhiNode>@ merge: v7 values: i108 i44  <|@  <|@
f <@#|@fixed with next>@ <|@
tid v7 <|@
d <@d|@=== Debug Properties ===
canEndsGuestSafepoint: true
canEndsSafepoint: true
canNeverOverflow: false
compilerInverted: false
disableCounted: false
hasSpeculationFence: false
loopOrigFrequency: 1.0
loopType: SIMPLE_LOOP
nextEndIndex: 1
nodeSourcePosition: at MatMul.MatMul.MultiplyLoop(MatMul.java:35) [bci: 2]
osrLoop: false
peelings: 0
rotated: false
splits: 0
stamp: void
stripMinedInner: false
stripMinedLimit: -1
stripMinedOuter: false
unrollFactor: 1
unswitches: 0
=== Inputs ===
stateAfter: - 
protectedNonOverflowingUnsigned: - 
overflowGuard: - 
interIterationAliasingGuard: - 
ends: v6 
=== Succesors ===
next: v15 
=== Usages ===
i8 v12 v45 
=== Predecessor ===
- >@ <|@
instruction <@LoopBegin|@org.graalvm.compiler.nodes.LoopBeginNode>@ stateAfter: - protectedNonOverflowingUnsigned: - overflowGuard: - interIterationAliasingGuard: - ends: v6 #next: v15  <|@  <|@
f <@~|@floating>@ <|@
tid v11 <|@
d <@d|@=== Debug Properties ===
condition: LT
nodeSourcePosition: at MatMul.MatMul.MultiplyLoop(MatMul.java:35) [bci: 6]
op: org.graalvm.compiler.nodes.calc.IntegerLessThanNode$LessThanOp@33dc3b9e
stamp: void
unorderedIsTrue: false
=== Inputs ===
x: i8 
y: i10 
=== Succesors ===
=== Usages ===
v15 
=== Predecessor ===
- >@ <|@
instruction <@<|@org.graalvm.compiler.nodes.calc.IntegerLessThanNode>@ x: i8 y: i10  <|@  <|@
f <@*|@fixed>@ <|@
tid v15 <|@
d <@d|@=== Debug Properties ===
nodeSourcePosition: at MatMul.MatMul.MultiplyLoop(MatMul.java:35) [bci: 6]
profileData: UNKNOWN designatedSuccessorProbability: 0.5
stamp: void
=== Inputs ===
condition: v11 
=== Succesors ===
trueSuccessor: v14 
falseSuccessor: v12 
=== Usages ===
=== Predecessor ===
v7 >@ <|@
instruction <@If|@org.graalvm.compiler.nodes.IfNode>@ condition: v11 #trueSuccessor: v14 #falseSuccessor: v12  <|@  <|@
    end_IR
  end_block
  begin_block
    name "B2"
    from_bci -1
    to_bci -1
    predecessors "B1" 
    successors "B3" 
    xhandlers
    flags 
    loop_index 0
    loop_depth 1
    probability 4607182418800017408
    begin_IR
      HIR
f <@#|@fixed with next>@ <|@
tid v14 <|@
d <@d|@=== Debug Properties ===
hasSpeculationFence: false
nodeSourcePosition: at MatMul.MatMul.MultiplyLoop(MatMul.java:36) [bci: 9]
stamp: void
=== Inputs ===
=== Succesors ===
next: v16 
=== Usages ===
=== Predecessor ===
v15 >@ <|@
instruction <@Begin|@org.graalvm.compiler.nodes.BeginNode>@ #next: v16  <|@  <|@
f <@~|@floating>@ <|@
tid i96 <|@
d <@d|@=== Debug Properties ===
nodeSourcePosition: at uk.ac.manchester.tornado.api.types.utils.StorageFormats.toRowMajor(StorageFormats.java:60) [bci: 2]
at uk.ac.manchester.tornado.api.types.matrix.Matrix2DFloat.set(Matrix2DFloat.java:110) [bci: 10]
at MatMul.MatMul.MultiplyLoop(MatMul.java:41) [bci: 67]
stamp: i32 [-2147483648 - 2147482624] bits:x...x0000000000
=== Inputs ===
x: i8 
y: i95 
=== Succesors ===
=== Usages ===
i137 
=== Predecessor ===
- >@ <|@
instruction <@<<|@org.graalvm.compiler.nodes.calc.LeftShiftNode>@ x: i8 y: i95  <|@  <|@
f <@~|@floating>@ <|@
tid i137 <|@
d <@d|@=== Debug Properties ===
stamp: i32 [-2147483642 - 2147482630] bits:x...x0000000110
=== Inputs ===
x: i96 
y: i87 
=== Succesors ===
=== Usages ===
i138 i139 
=== Predecessor ===
- >@ <|@
instruction <@+|@org.graalvm.compiler.nodes.calc.AddNode>@ x: i96 y: i87  <|@  <|@
f <@*|@fixed>@ <|@
tid v16 <|@
d <@d|@=== Debug Properties ===
nodeSourcePosition: at MatMul.MatMul.MultiplyLoop(MatMul.java:36) [bci: 12]
stamp: void
=== Inputs ===
=== Succesors ===
=== Usages ===
v17 
=== Predecessor ===
v14 >@ <|@
instruction <@EndNode|@org.graalvm.compiler.nodes.EndNode>@  <|@  <|@
    end_IR
  end_block
  begin_block
    name "B3"
    from_bci -1
    to_bci -1
    predecessors "B2" "B7" 
    successors "B4" "B8" 
    xhandlers
    flags "llh" 
    loop_index 1
    loop_depth 2
    probability 4611686018427387904
    begin_IR
      HIR
f <@~|@floating>@ <|@
tid i18 <|@
d <@d|@=== Debug Properties ===
nodeSourcePosition: at MatMul.MatMul.MultiplyLoop(MatMul.java:36) [bci: 12]
stamp: i32
valueDescription: i32
=== Inputs ===
merge: v17 
values: i104 i42 
=== Succesors ===
=== Usages ===
i140 v20 i42 i138 
=== Predecessor ===
- >@ <|@
instruction <@ValuePhi|@org.graalvm.compiler.nodes.ValuePhiNode>@ merge: v17 values: i104 i42  <|@  <|@
f <@#|@fixed with next>@ <|@
tid v17 <|@
d <@d|@=== Debug Properties ===
canEndsGuestSafepoint: true
canEndsSafepoint: true
canNeverOverflow: false
compilerInverted: false
disableCounted: false
hasSpeculationFence: false
loopOrigFrequency: 1.0
loopType: SIMPLE_LOOP
nextEndIndex: 1
nodeSourcePosition: at MatMul.MatMul.MultiplyLoop(MatMul.java:36) [bci: 12]
osrLoop: false
peelings: 0
rotated: false
splits: 0
stamp: void
stripMinedInner: false
stripMinedLimit: -1
stripMinedOuter: false
unrollFactor: 1
unswitches: 0
=== Inputs ===
stateAfter: - 
protectedNonOverflowingUnsigned: - 
overflowGuard: - 
interIterationAliasingGuard: - 
ends: v16 
=== Succesors ===
next: v24 
=== Usages ===
i18 v21 v43 
=== Predecessor ===
- >@ <|@
instruction <@LoopBegin|@org.graalvm.compiler.nodes.LoopBeginNode>@ stateAfter: - protectedNonOverflowingUnsigned: - overflowGuard: - interIterationAliasingGuard: - ends: v16 #next: v24  <|@  <|@
f <@~|@floating>@ <|@
tid v20 <|@
d <@d|@=== Debug Properties ===
condition: LT
nodeSourcePosition: at MatMul.MatMul.MultiplyLoop(MatMul.java:36) [bci: 17]
op: org.graalvm.compiler.nodes.calc.IntegerLessThanNode$LessThanOp@33dc3b9e
stamp: void
unorderedIsTrue: false
=== Inputs ===
x: i18 
y: i10 
=== Succesors ===
=== Usages ===
v24 
=== Predecessor ===
- >@ <|@
instruction <@<|@org.graalvm.compiler.nodes.calc.IntegerLessThanNode>@ x: i18 y: i10  <|@  <|@
f <@*|@fixed>@ <|@
tid v24 <|@
d <@d|@=== Debug Properties ===
nodeSourcePosition: at MatMul.MatMul.MultiplyLoop(MatMul.java:36) [bci: 17]
profileData: UNKNOWN designatedSuccessorProbability: 0.5
stamp: void
=== Inputs ===
condition: v20 
=== Succesors ===
trueSuccessor: v23 
falseSuccessor: v21 
=== Usages ===
=== Predecessor ===
v17 >@ <|@
instruction <@If|@org.graalvm.compiler.nodes.IfNode>@ condition: v20 #trueSuccessor: v23 #falseSuccessor: v21  <|@  <|@
    end_IR
  end_block
  begin_block
    name "B4"
    from_bci -1
    to_bci -1
    predecessors "B3" 
    successors "B5" 
    xhandlers
    flags 
    loop_index 1
    loop_depth 2
    probability 4607182418800017408
    begin_IR
      HIR
f <@#|@fixed with next>@ <|@
tid v23 <|@
d <@d|@=== Debug Properties ===
hasSpeculationFence: false
nodeSourcePosition: at MatMul.MatMul.MultiplyLoop(MatMul.java:37) [bci: 20]
stamp: void
=== Inputs ===
=== Succesors ===
next: v26 
=== Usages ===
=== Predecessor ===
v24 >@ <|@
instruction <@Begin|@org.graalvm.compiler.nodes.BeginNode>@ #next: v26  <|@  <|@
f <@~|@floating>@ <|@
tid i140 <|@
d <@d|@=== Debug Properties ===
stamp: i32
=== Inputs ===
x: i18 
y: i87 
=== Succesors ===
=== Usages ===
i141 
=== Predecessor ===
- >@ <|@
instruction <@+|@org.graalvm.compiler.nodes.calc.AddNode>@ x: i18 y: i87  <|@  <|@
f <@*|@fixed>@ <|@
tid v26 <|@
d <@d|@=== Debug Properties ===
nodeSourcePosition: at MatMul.MatMul.MultiplyLoop(MatMul.java:38) [bci: 26]
stamp: void
=== Inputs ===
=== Succesors ===
=== Usages ===
v27 
=== Predecessor ===
v23 >@ <|@
instruction <@EndNode|@org.graalvm.compiler.nodes.EndNode>@  <|@  <|@
    end_IR
  end_block
  begin_block
    name "B5"
    from_bci -1
    to_bci -1
    predecessors "B4" "B6" 
    successors "B6" "B7" 
    xhandlers
    flags "llh" 
    loop_index 2
    loop_depth 3
    probability 4611686018427387904
    begin_IR
      HIR
f <@~|@floating>@ <|@
tid f28 <|@
d <@d|@=== Debug Properties ===
nodeSourcePosition: at MatMul.MatMul.MultiplyLoop(MatMul.java:38) [bci: 26]
stamp: f32
valueDescription: f32
=== Inputs ===
merge: v27 
values: f25 f151 
=== Succesors ===
=== Usages ===
f151 v123 
=== Predecessor ===
- >@ <|@
instruction <@ValuePhi|@org.graalvm.compiler.nodes.ValuePhiNode>@ merge: v27 values: f25 f151  <|@  <|@
f <@~|@floating>@ <|@
tid i29 <|@
d <@d|@=== Debug Properties ===
nodeSourcePosition: at MatMul.MatMul.MultiplyLoop(MatMul.java:38) [bci: 26]
stamp: i32
valueDescription: i32
=== Inputs ===
merge: v27 
values: i5 i40 
=== Succesors ===
=== Usages ===
i97 v31 i40 i139 
=== Predecessor ===
- >@ <|@
instruction <@ValuePhi|@org.graalvm.compiler.nodes.ValuePhiNode>@ merge: v27 values: i5 i40  <|@  <|@
f <@#|@fixed with next>@ <|@
tid v27 <|@
d <@d|@=== Debug Properties ===
canEndsGuestSafepoint: true
canEndsSafepoint: true
canNeverOverflow: false
compilerInverted: false
disableCounted: false
hasSpeculationFence: false
loopOrigFrequency: 1.0
loopType: SIMPLE_LOOP
nextEndIndex: 1
nodeSourcePosition: at MatMul.MatMul.MultiplyLoop(MatMul.java:38) [bci: 26]
osrLoop: false
peelings: 0
rotated: false
splits: 0
stamp: void
stripMinedInner: false
stripMinedLimit: -1
stripMinedOuter: false
unrollFactor: 1
unswitches: 0
=== Inputs ===
stateAfter: - 
protectedNonOverflowingUnsigned: - 
overflowGuard: - 
interIterationAliasingGuard: - 
ends: v26 
=== Succesors ===
next: v36 
=== Usages ===
f28 i29 v32 v41 
=== Predecessor ===
- >@ <|@
instruction <@LoopBegin|@org.graalvm.compiler.nodes.LoopBeginNode>@ stateAfter: - protectedNonOverflowingUnsigned: - overflowGuard: - interIterationAliasingGuard: - ends: v26 #next: v36  <|@  <|@
f <@~|@floating>@ <|@
tid v31 <|@
d <@d|@=== Debug Properties ===
condition: LT
nodeSourcePosition: at MatMul.MatMul.MultiplyLoop(MatMul.java:38) [bci: 31]
op: org.graalvm.compiler.nodes.calc.IntegerLessThanNode$LessThanOp@33dc3b9e
stamp: void
unorderedIsTrue: false
=== Inputs ===
x: i29 
y: i10 
=== Succesors ===
=== Usages ===
v36 
=== Predecessor ===
- >@ <|@
instruction <@<|@org.graalvm.compiler.nodes.calc.IntegerLessThanNode>@ x: i29 y: i10  <|@  <|@
f <@*|@fixed>@ <|@
tid v36 <|@
d <@d|@=== Debug Properties ===
nodeSourcePosition: at MatMul.MatMul.MultiplyLoop(MatMul.java:38) [bci: 31]
profileData: UNKNOWN designatedSuccessorProbability: 0.5
stamp: void
=== Inputs ===
condition: v31 
=== Succesors ===
trueSuccessor: v35 
falseSuccessor: v32 
=== Usages ===
=== Predecessor ===
v27 >@ <|@
instruction <@If|@org.graalvm.compiler.nodes.IfNode>@ condition: v31 #trueSuccessor: v35 #falseSuccessor: v32  <|@  <|@
    end_IR
  end_block
  begin_block
    name "B6"
    from_bci -1
    to_bci -1
    predecessors "B5" 
    successors "B5" 
    xhandlers
    flags "lle" 
    loop_index 2
    loop_depth 3
    probability 4607182418800017408
    begin_IR
      HIR
f <@#|@fixed with next>@ <|@
tid v35 <|@
d <@d|@=== Debug Properties ===
hasSpeculationFence: false
nodeSourcePosition: at MatMul.MatMul.MultiplyLoop(MatMul.java:39) [bci: 34]
stamp: void
=== Inputs ===
=== Succesors ===
next: a115 
=== Usages ===
=== Predecessor ===
v36 >@ <|@
instruction <@Begin|@org.graalvm.compiler.nodes.BeginNode>@ #next: a115  <|@  <|@
f <@#|@fixed with next>@ <|@
tid a115 <|@
d <@d|@=== Debug Properties ===
accessStamp: a# uk.ac.manchester.tornado.api.types.arrays.FloatArray
barrierType: NONE
deoptReasonAndAction: [null]
deoptSpeculation: [null]
extendKind: DEFAULT
forceFixed: false
location: Matrix2DFloat.storage
memoryOrder: [null]
nodeSourcePosition: at uk.ac.manchester.tornado.api.types.matrix.Matrix2DFloat.get(Matrix2DFloat.java:106) [bci: 1]
at MatMul.MatMul.MultiplyLoop(MatMul.java:39) [bci: 40]
stamp: a# uk.ac.manchester.tornado.api.types.arrays.FloatArray
usedAsNullCheck: false
=== Inputs ===
stateBefore: - 
guard: - 
address: v148 
lastLocationAccess: - 
=== Succesors ===
next: f116 
=== Usages ===
j100 
=== Predecessor ===
v35 >@ <|@
instruction <@Read|@org.graalvm.compiler.nodes.memory.ReadNode>@ stateBefore: - guard: - address: v148 lastLocationAccess: - #next: f116  <|@  <|@
f <@~|@floating>@ <|@
tid j100 <|@
d <@d|@=== Debug Properties ===
stamp: i64
=== Inputs ===
base: a1 
offset: a115 
=== Succesors ===
=== Usages ===
v146 
=== Predecessor ===
- >@ <|@
instruction <@TornadoAddressArithmetic|@uk.ac.manchester.tornado.runtime.graal.nodes.calc.TornadoAddressArithmeticNode>@ base: a1 offset: a115  <|@  <|@
f <@~|@floating>@ <|@
tid i139 <|@
d <@d|@=== Debug Properties ===
stamp: i32
=== Inputs ===
x: i29 
y: i137 
=== Succesors ===
=== Usages ===
j71 
=== Predecessor ===
- >@ <|@
instruction <@+|@org.graalvm.compiler.nodes.calc.AddNode>@ x: i29 y: i137  <|@  <|@
f <@~|@floating>@ <|@
tid j71 <|@
d <@d|@=== Debug Properties ===
inputBits: 32
nodeSourcePosition: at uk.ac.manchester.tornado.api.types.arrays.FloatArray.get(FloatArray.java:177) [bci: 13]
at uk.ac.manchester.tornado.api.types.matrix.Matrix2DFloat.get(Matrix2DFloat.java:106) [bci: 13]
at MatMul.MatMul.MultiplyLoop(MatMul.java:39) [bci: 40]
resultBits: 64
stamp: i64 [-2147483648 - 2147483647]
=== Inputs ===
value: i139 
=== Succesors ===
=== Usages ===
j74 
=== Predecessor ===
- >@ <|@
instruction <@SignExtend|@org.graalvm.compiler.nodes.calc.SignExtendNode>@ value: i139  <|@  <|@
f <@~|@floating>@ <|@
tid j74 <|@
d <@d|@=== Debug Properties ===
nodeSourcePosition: at uk.ac.manchester.tornado.api.types.arrays.FloatArray.get(FloatArray.java:177) [bci: 14]
at uk.ac.manchester.tornado.api.types.matrix.Matrix2DFloat.get(Matrix2DFloat.java:106) [bci: 13]
at MatMul.MatMul.MultiplyLoop(MatMul.java:39) [bci: 40]
stamp: i64 [-8589934592 - 8589934588] bits:x...x00
=== Inputs ===
x: j71 
y: i59 
=== Succesors ===
=== Usages ===
v146 
=== Predecessor ===
- >@ <|@
instruction <@<<|@org.graalvm.compiler.nodes.calc.LeftShiftNode>@ x: j71 y: i59  <|@  <|@
f <@~|@floating>@ <|@
tid v146 <|@
d <@d|@=== Debug Properties ===
memoryRegister: uk.ac.manchester.tornado.drivers.opencl.graal.OCLArchitecture$OCLMemoryBase@73393584
stamp: void*
=== Inputs ===
base: j100 
index: j74 
=== Succesors ===
=== Usages ===
f116 
=== Predecessor ===
- >@ <|@
instruction <@OCLAddress|@uk.ac.manchester.tornado.drivers.opencl.graal.lir.OCLAddressNode>@ base: j100 index: j74  <|@  <|@
f <@#|@fixed with next>@ <|@
tid f116 <|@
d <@d|@=== Debug Properties ===
accessStamp: f32
barrierType: NONE
deoptReasonAndAction: [null]
deoptSpeculation: [null]
extendKind: DEFAULT
forceFixed: true
location: ANY_LOCATION
memoryOrder: PLAIN
nodeSourcePosition: at uk.ac.manchester.tornado.api.types.arrays.FloatArray.get(FloatArray.java:177) [bci: 14]
at uk.ac.manchester.tornado.api.types.matrix.Matrix2DFloat.get(Matrix2DFloat.java:106) [bci: 13]
at MatMul.MatMul.MultiplyLoop(MatMul.java:39) [bci: 40]
stamp: f32
usedAsNullCheck: false
=== Inputs ===
stateBefore: - 
guard: - 
address: v146 
lastLocationAccess: - 
=== Succesors ===
next: a118 
=== Usages ===
f151 
=== Predecessor ===
a115 >@ <|@
instruction <@Read|@org.graalvm.compiler.nodes.memory.ReadNode>@ stateBefore: - guard: - address: v146 lastLocationAccess: - #next: a118  <|@  <|@
f <@#|@fixed with next>@ <|@
tid a118 <|@
d <@d|@=== Debug Properties ===
accessStamp: a# uk.ac.manchester.tornado.api.types.arrays.FloatArray
barrierType: NONE
deoptReasonAndAction: [null]
deoptSpeculation: [null]
extendKind: DEFAULT
forceFixed: false
location: Matrix2DFloat.storage
memoryOrder: [null]
nodeSourcePosition: at uk.ac.manchester.tornado.api.types.matrix.Matrix2DFloat.get(Matrix2DFloat.java:106) [bci: 1]
at MatMul.MatMul.MultiplyLoop(MatMul.java:39) [bci: 48]
stamp: a# uk.ac.manchester.tornado.api.types.arrays.FloatArray
usedAsNullCheck: false
=== Inputs ===
stateBefore: - 
guard: - 
address: v149 
lastLocationAccess: - 
=== Succesors ===
next: f119 
=== Usages ===
j101 
=== Predecessor ===
f116 >@ <|@
instruction <@Read|@org.graalvm.compiler.nodes.memory.ReadNode>@ stateBefore: - guard: - address: v149 lastLocationAccess: - #next: f119  <|@  <|@
f <@~|@floating>@ <|@
tid j101 <|@
d <@d|@=== Debug Properties ===
stamp: i64
=== Inputs ===
base: a2 
offset: a118 
=== Succesors ===
=== Usages ===
v147 
=== Predecessor ===
- >@ <|@
instruction <@TornadoAddressArithmetic|@uk.ac.manchester.tornado.runtime.graal.nodes.calc.TornadoAddressArithmeticNode>@ base: a2 offset: a118  <|@  <|@
f <@~|@floating>@ <|@
tid i97 <|@
d <@d|@=== Debug Properties ===
nodeSourcePosition: at uk.ac.manchester.tornado.api.types.utils.StorageFormats.toRowMajor(StorageFormats.java:60) [bci: 2]
at uk.ac.manchester.tornado.api.types.matrix.Matrix2DFloat.get(Matrix2DFloat.java:106) [bci: 10]
at MatMul.MatMul.MultiplyLoop(MatMul.java:39) [bci: 48]
stamp: i32 [-2147483648 - 2147482624] bits:x...x0000000000
=== Inputs ===
x: i29 
y: i95 
=== Succesors ===
=== Usages ===
i141 
=== Predecessor ===
- >@ <|@
instruction <@<<|@org.graalvm.compiler.nodes.calc.LeftShiftNode>@ x: i29 y: i95  <|@  <|@
f <@~|@floating>@ <|@
tid i141 <|@
d <@d|@=== Debug Properties ===
stamp: i32
=== Inputs ===
x: i97 
y: i140 
=== Succesors ===
=== Usages ===
j83 
=== Predecessor ===
- >@ <|@
instruction <@+|@org.graalvm.compiler.nodes.calc.AddNode>@ x: i97 y: i140  <|@  <|@
f <@~|@floating>@ <|@
tid j83 <|@
d <@d|@=== Debug Properties ===
inputBits: 32
nodeSourcePosition: at uk.ac.manchester.tornado.api.types.arrays.FloatArray.get(FloatArray.java:177) [bci: 13]
at uk.ac.manchester.tornado.api.types.matrix.Matrix2DFloat.get(Matrix2DFloat.java:106) [bci: 13]
at MatMul.MatMul.MultiplyLoop(MatMul.java:39) [bci: 48]
resultBits: 64
stamp: i64 [-2147483648 - 2147483647]
=== Inputs ===
value: i141 
=== Succesors ===
=== Usages ===
j86 
=== Predecessor ===
- >@ <|@
instruction <@SignExtend|@org.graalvm.compiler.nodes.calc.SignExtendNode>@ value: i141  <|@  <|@
f <@~|@floating>@ <|@
tid j86 <|@
d <@d|@=== Debug Properties ===
nodeSourcePosition: at uk.ac.manchester.tornado.api.types.arrays.FloatArray.get(FloatArray.java:177) [bci: 14]
at uk.ac.manchester.tornado.api.types.matrix.Matrix2DFloat.get(Matrix2DFloat.java:106) [bci: 13]
at MatMul.MatMul.MultiplyLoop(MatMul.java:39) [bci: 48]
stamp: i64 [-8589934592 - 8589934588] bits:x...x00
=== Inputs ===
x: j83 
y: i59 
=== Succesors ===
=== Usages ===
v147 
=== Predecessor ===
- >@ <|@
instruction <@<<|@org.graalvm.compiler.nodes.calc.LeftShiftNode>@ x: j83 y: i59  <|@  <|@
f <@~|@floating>@ <|@
tid v147 <|@
d <@d|@=== Debug Properties ===
memoryRegister: uk.ac.manchester.tornado.drivers.opencl.graal.OCLArchitecture$OCLMemoryBase@73393584
stamp: void*
=== Inputs ===
base: j101 
index: j86 
=== Succesors ===
=== Usages ===
f119 
=== Predecessor ===
- >@ <|@
instruction <@OCLAddress|@uk.ac.manchester.tornado.drivers.opencl.graal.lir.OCLAddressNode>@ base: j101 index: j86  <|@  <|@
f <@#|@fixed with next>@ <|@
tid f119 <|@
d <@d|@=== Debug Properties ===
accessStamp: f32
barrierType: NONE
deoptReasonAndAction: [null]
deoptSpeculation: [null]
extendKind: DEFAULT
forceFixed: true
location: ANY_LOCATION
memoryOrder: PLAIN
nodeSourcePosition: at uk.ac.manchester.tornado.api.types.arrays.FloatArray.get(FloatArray.java:177) [bci: 14]
at uk.ac.manchester.tornado.api.types.matrix.Matrix2DFloat.get(Matrix2DFloat.java:106) [bci: 13]
at MatMul.MatMul.MultiplyLoop(MatMul.java:39) [bci: 48]
stamp: f32
usedAsNullCheck: false
=== Inputs ===
stateBefore: - 
guard: - 
address: v147 
lastLocationAccess: - 
=== Succesors ===
next: v41 
=== Usages ===
f151 
=== Predecessor ===
a118 >@ <|@
instruction <@Read|@org.graalvm.compiler.nodes.memory.ReadNode>@ stateBefore: - guard: - address: v147 lastLocationAccess: - #next: v41  <|@  <|@
f <@~|@floating>@ <|@
tid f151 <|@
d <@d|@=== Debug Properties ===
stamp: f32
=== Inputs ===
x: f116 
y: f119 
z: f28 
=== Succesors ===
=== Usages ===
f28 
=== Predecessor ===
- >@ <|@
instruction <@OCL-FMA|@uk.ac.manchester.tornado.drivers.opencl.graal.nodes.OCLFMANode>@ x: f116 y: f119 z: f28  <|@  <|@
f <@~|@floating>@ <|@
tid i40 <|@
d <@d|@=== Debug Properties ===
nodeSourcePosition: at MatMul.MatMul.MultiplyLoop(MatMul.java:38) [bci: 55]
stamp: i32
=== Inputs ===
x: i29 
y: i39 
=== Succesors ===
=== Usages ===
i29 
=== Predecessor ===
- >@ <|@
instruction <@+|@org.graalvm.compiler.nodes.calc.AddNode>@ x: i29 y: i39  <|@  <|@
f <@*|@fixed>@ <|@
tid v41 <|@
d <@d|@=== Debug Properties ===
canGuestSafepoint: true
canSafepoint: true
endIndex: 0
nodeSourcePosition: at MatMul.MatMul.MultiplyLoop(MatMul.java:38) [bci: 26]
stamp: void
=== Inputs ===
loopBegin: v27 
=== Succesors ===
=== Usages ===
=== Predecessor ===
f119 >@ <|@
instruction <@LoopEnd|@org.graalvm.compiler.nodes.LoopEndNode>@ loopBegin: v27  <|@  <|@
    end_IR
  end_block
  begin_block
    name "B7"
    from_bci -1
    to_bci -1
    predecessors "B5" 
    successors "B3" 
    xhandlers
    flags "lle" 
    loop_index 1
    loop_depth 2
    probability 4607182418800017408
    begin_IR
      HIR
f <@#|@fixed with next>@ <|@
tid v32 <|@
d <@d|@=== Debug Properties ===
hasSpeculationFence: false
nodeSourcePosition: at MatMul.MatMul.MultiplyLoop(MatMul.java:41) [bci: 61]
stamp: void
=== Inputs ===
stateAfter: - 
loopBegin: v27 
=== Succesors ===
next: a122 
=== Usages ===
=== Predecessor ===
v36 >@ <|@
instruction <@LoopExit|@org.graalvm.compiler.nodes.LoopExitNode>@ stateAfter: - loopBegin: v27 #next: a122  <|@  <|@
f <@#|@fixed with next>@ <|@
tid a122 <|@
d <@d|@=== Debug Properties ===
accessStamp: a# uk.ac.manchester.tornado.api.types.arrays.FloatArray
barrierType: NONE
deoptReasonAndAction: [null]
deoptSpeculation: [null]
extendKind: DEFAULT
forceFixed: false
location: Matrix2DFloat.storage
memoryOrder: [null]
nodeSourcePosition: at uk.ac.manchester.tornado.api.types.matrix.Matrix2DFloat.set(Matrix2DFloat.java:110) [bci: 1]
at MatMul.MatMul.MultiplyLoop(MatMul.java:41) [bci: 67]
stamp: a# uk.ac.manchester.tornado.api.types.arrays.FloatArray
usedAsNullCheck: false
=== Inputs ===
stateBefore: - 
guard: - 
address: v150 
lastLocationAccess: - 
=== Succesors ===
next: v123 
=== Usages ===
j102 
=== Predecessor ===
v32 >@ <|@
instruction <@Read|@org.graalvm.compiler.nodes.memory.ReadNode>@ stateBefore: - guard: - address: v150 lastLocationAccess: - #next: v123  <|@  <|@
f <@~|@floating>@ <|@
tid j102 <|@
d <@d|@=== Debug Properties ===
stamp: i64
=== Inputs ===
base: a3 
offset: a122 
=== Succesors ===
=== Usages ===
v145 
=== Predecessor ===
- >@ <|@
instruction <@TornadoAddressArithmetic|@uk.ac.manchester.tornado.runtime.graal.nodes.calc.TornadoAddressArithmeticNode>@ base: a3 offset: a122  <|@  <|@
f <@~|@floating>@ <|@
tid i138 <|@
d <@d|@=== Debug Properties ===
stamp: i32
=== Inputs ===
x: i18 
y: i137 
=== Succesors ===
=== Usages ===
j55 
=== Predecessor ===
- >@ <|@
instruction <@+|@org.graalvm.compiler.nodes.calc.AddNode>@ x: i18 y: i137  <|@  <|@
f <@~|@floating>@ <|@
tid j55 <|@
d <@d|@=== Debug Properties ===
inputBits: 32
nodeSourcePosition: at uk.ac.manchester.tornado.api.types.arrays.FloatArray.set(FloatArray.java:166) [bci: 13]
at uk.ac.manchester.tornado.api.types.matrix.Matrix2DFloat.set(Matrix2DFloat.java:110) [bci: 14]
at MatMul.MatMul.MultiplyLoop(MatMul.java:41) [bci: 67]
resultBits: 64
stamp: i64 [-2147483648 - 2147483647]
=== Inputs ===
value: i138 
=== Succesors ===
=== Usages ===
j60 
=== Predecessor ===
- >@ <|@
instruction <@SignExtend|@org.graalvm.compiler.nodes.calc.SignExtendNode>@ value: i138  <|@  <|@
f <@~|@floating>@ <|@
tid j60 <|@
d <@d|@=== Debug Properties ===
nodeSourcePosition: at uk.ac.manchester.tornado.api.types.arrays.FloatArray.set(FloatArray.java:166) [bci: 15]
at uk.ac.manchester.tornado.api.types.matrix.Matrix2DFloat.set(Matrix2DFloat.java:110) [bci: 14]
at MatMul.MatMul.MultiplyLoop(MatMul.java:41) [bci: 67]
stamp: i64 [-8589934592 - 8589934588] bits:x...x00
=== Inputs ===
x: j55 
y: i59 
=== Succesors ===
=== Usages ===
v145 
=== Predecessor ===
- >@ <|@
instruction <@<<|@org.graalvm.compiler.nodes.calc.LeftShiftNode>@ x: j55 y: i59  <|@  <|@
f <@~|@floating>@ <|@
tid v145 <|@
d <@d|@=== Debug Properties ===
memoryRegister: uk.ac.manchester.tornado.drivers.opencl.graal.OCLArchitecture$OCLMemoryBase@73393584
stamp: void*
=== Inputs ===
base: j102 
index: j60 
=== Succesors ===
=== Usages ===
v123 
=== Predecessor ===
- >@ <|@
instruction <@OCLAddress|@uk.ac.manchester.tornado.drivers.opencl.graal.lir.OCLAddressNode>@ base: j102 index: j60  <|@  <|@
f <@#|@fixed with next>@ <|@
tid v123 <|@
d <@d|@=== Debug Properties ===
barrierType: NONE
deoptReasonAndAction: [null]
deoptSpeculation: [null]
killedLocationIdentity: ANY_LOCATION
location: ANY_LOCATION
memoryOrder: PLAIN
nodeSourcePosition: at uk.ac.manchester.tornado.api.types.arrays.FloatArray.set(FloatArray.java:166) [bci: 15]
at uk.ac.manchester.tornado.api.types.matrix.Matrix2DFloat.set(Matrix2DFloat.java:110) [bci: 14]
at MatMul.MatMul.MultiplyLoop(MatMul.java:41) [bci: 67]
stamp: void
usedAsNullCheck: false
=== Inputs ===
stateBefore: - 
guard: - 
address: v145 
lastLocationAccess: - 
value: f28 
stateAfter: - 
=== Succesors ===
next: v43 
=== Usages ===
=== Predecessor ===
a122 >@ <|@
instruction <@Write|@org.graalvm.compiler.nodes.memory.WriteNode>@ stateBefore: - guard: - address: v145 lastLocationAccess: - value: f28 stateAfter: - #next: v43  <|@  <|@
f <@~|@floating>@ <|@
tid i42 <|@
d <@d|@=== Debug Properties ===
nodeSourcePosition: at MatMul.MatMul.MultiplyLoop(MatMul.java:36) [bci: 70]
stamp: i32
=== Inputs ===
x: i18 
y: i107 
=== Succesors ===
=== Usages ===
i18 
=== Predecessor ===
- >@ <|@
instruction <@+|@org.graalvm.compiler.nodes.calc.AddNode>@ x: i18 y: i107  <|@  <|@
f <@*|@fixed>@ <|@
tid v43 <|@
d <@d|@=== Debug Properties ===
canGuestSafepoint: true
canSafepoint: true
endIndex: 0
nodeSourcePosition: at MatMul.MatMul.MultiplyLoop(MatMul.java:36) [bci: 12]
stamp: void
=== Inputs ===
loopBegin: v17 
=== Succesors ===
=== Usages ===
=== Predecessor ===
v123 >@ <|@
instruction <@LoopEnd|@org.graalvm.compiler.nodes.LoopEndNode>@ loopBegin: v17  <|@  <|@
    end_IR
  end_block
  begin_block
    name "B8"
    from_bci -1
    to_bci -1
    predecessors "B3" 
    successors "B1" 
    xhandlers
    flags "lle" 
    loop_index 0
    loop_depth 1
    probability 4607182418800017408
    begin_IR
      HIR
f <@#|@fixed with next>@ <|@
tid v21 <|@
d <@d|@=== Debug Properties ===
hasSpeculationFence: false
nodeSourcePosition: at MatMul.MatMul.MultiplyLoop(MatMul.java:35) [bci: 76]
stamp: void
=== Inputs ===
stateAfter: - 
loopBegin: v17 
=== Succesors ===
next: v45 
=== Usages ===
=== Predecessor ===
v24 >@ <|@
instruction <@LoopExit|@org.graalvm.compiler.nodes.LoopExitNode>@ stateAfter: - loopBegin: v17 #next: v45  <|@  <|@
f <@~|@floating>@ <|@
tid i44 <|@
d <@d|@=== Debug Properties ===
nodeSourcePosition: at MatMul.MatMul.MultiplyLoop(MatMul.java:35) [bci: 76]
stamp: i32
=== Inputs ===
x: i8 
y: i111 
=== Succesors ===
=== Usages ===
i8 
=== Predecessor ===
- >@ <|@
instruction <@+|@org.graalvm.compiler.nodes.calc.AddNode>@ x: i8 y: i111  <|@  <|@
f <@*|@fixed>@ <|@
tid v45 <|@
d <@d|@=== Debug Properties ===
canGuestSafepoint: true
canSafepoint: true
endIndex: 0
nodeSourcePosition: at MatMul.MatMul.MultiplyLoop(MatMul.java:35) [bci: 2]
stamp: void
=== Inputs ===
loopBegin: v7 
=== Succesors ===
=== Usages ===
=== Predecessor ===
v21 >@ <|@
instruction <@LoopEnd|@org.graalvm.compiler.nodes.LoopEndNode>@ loopBegin: v7  <|@  <|@
    end_IR
  end_block
  begin_block
    name "B9"
    from_bci -1
    to_bci -1
    predecessors "B1" 
    successors 
    xhandlers
    flags 
    probability 4607182418800017408
    begin_IR
      HIR
f <@#|@fixed with next>@ <|@
tid v12 <|@
d <@d|@=== Debug Properties ===
hasSpeculationFence: false
nodeSourcePosition: at MatMul.MatMul.MultiplyLoop(MatMul.java:44) [bci: 82]
stamp: void
=== Inputs ===
stateAfter: - 
loopBegin: v7 
=== Succesors ===
next: v46 
=== Usages ===
=== Predecessor ===
v15 >@ <|@
instruction <@LoopExit|@org.graalvm.compiler.nodes.LoopExitNode>@ stateAfter: - loopBegin: v7 #next: v46  <|@  <|@
f <@*|@fixed>@ <|@
tid v46 <|@
d <@d|@=== Debug Properties ===
nodeSourcePosition: at MatMul.MatMul.MultiplyLoop(MatMul.java:44) [bci: 82]
stamp: void
=== Inputs ===
memoryMap: - 
result: - 
=== Succesors ===
=== Usages ===
=== Predecessor ===
v12 >@ <|@
instruction <@Return|@org.graalvm.compiler.nodes.ReturnNode>@ memoryMap: - result: -  <|@  <|@
    end_IR
  end_block
end_cfg
begin_cfg
  name "After linear scan order"
  begin_block
    name "B0"
    from_bci -1
    to_bci -1
    predecessors 
    successors "B1" 
    xhandlers
    flags 
    probability 4607182418800017408
  end_block
  begin_block
    name "B1"
    from_bci -1
    to_bci -1
    predecessors "B0" "B8" 
    successors "B2" "B9" 
    xhandlers
    flags "llh" 
    loop_index 0
    loop_depth 1
    probability 4611686018427387904
  end_block
  begin_block
    name "B2"
    from_bci -1
    to_bci -1
    predecessors "B1" 
    successors "B3" 
    xhandlers
    flags 
    loop_index 0
    loop_depth 1
    probability 4607182418800017408
  end_block
  begin_block
    name "B3"
    from_bci -1
    to_bci -1
    predecessors "B2" "B7" 
    successors "B4" "B8" 
    xhandlers
    flags "llh" 
    loop_index 1
    loop_depth 2
    probability 4611686018427387904
  end_block
  begin_block
    name "B4"
    from_bci -1
    to_bci -1
    predecessors "B3" 
    successors "B5" 
    xhandlers
    flags 
    loop_index 1
    loop_depth 2
    probability 4607182418800017408
  end_block
  begin_block
    name "B5"
    from_bci -1
    to_bci -1
    predecessors "B4" "B6" 
    successors "B6" "B7" 
    xhandlers
    flags "llh" 
    loop_index 2
    loop_depth 3
    probability 4611686018427387904
  end_block
  begin_block
    name "B6"
    from_bci -1
    to_bci -1
    predecessors "B5" 
    successors "B5" 
    xhandlers
    flags "lle" 
    loop_index 2
    loop_depth 3
    probability 4607182418800017408
  end_block
  begin_block
    name "B7"
    from_bci -1
    to_bci -1
    predecessors "B5" 
    successors "B3" 
    xhandlers
    flags "lle" 
    loop_index 1
    loop_depth 2
    probability 4607182418800017408
  end_block
  begin_block
    name "B8"
    from_bci -1
    to_bci -1
    predecessors "B3" 
    successors "B1" 
    xhandlers
    flags "lle" 
    loop_index 0
    loop_depth 1
    probability 4607182418800017408
  end_block
  begin_block
    name "B9"
    from_bci -1
    to_bci -1
    predecessors "B1" 
    successors 
    xhandlers
    flags 
    probability 4607182418800017408
  end_block
end_cfg
begin_bytecodes
     0: iconst_0      
     1: istore_3      
     2: iload_3       
     3: sipush        1024
     6: if_icmpge     82
     9: iconst_0      
    10: istore        4
    12: iload         4
    14: sipush        1024
    17: if_icmpge     76
    20: fconst_0      
    21: fstore        5
    23: iconst_0      
    24: istore        6
    26: iload         6
    28: sipush        1024
    31: if_icmpge     61
    34: fload         5
    36: aload_0       
    37: iload_3       
    38: iload         6
    40: invokevirtual #1          // uk.ac.manchester.tornado.api.types.matrix.Matrix2DFloat.get:(int, int)float
    43: aload_1       
    44: iload         6
    46: iload         4
    48: invokevirtual #1          // uk.ac.manchester.tornado.api.types.matrix.Matrix2DFloat.get:(int, int)float
    51: fmul          
    52: fadd          
    53: fstore        5
    55: iinc          
    58: goto          26
    61: aload_2       
    62: iload_3       
    63: iload         4
    65: fload         5
    67: invokevirtual #2          // uk.ac.manchester.tornado.api.types.matrix.Matrix2DFloat.set:(int, int, float)void
    70: iinc          
    73: goto          12
    76: iinc          
    79: goto          2
    82: return        
   <|@
end_bytecodes
begin_cfg
  name "After OCLLIRGeneration"
  begin_block
    name "B0"
    from_bci -1
    to_bci -1
    predecessors 
    successors "B1" 
    xhandlers
    flags 
    probability 4607182418800017408
    begin_IR
      LIR
      nr   -1  <|@ instruction [] = LABEL alignment: 0 numbPhis: 0 label: ? <|@ <|@
      nr   -1  <|@ instruction v0|ULONG = ASSIGN (ulong) A <|@ <|@
      nr   -1  <|@ instruction v1|ULONG = ASSIGN (ulong) B <|@ <|@
      nr   -1  <|@ instruction v2|ULONG = ASSIGN (ulong) C <|@ <|@
      nr   -1  <|@ instruction v3|INT = ASSIGN get_global_size(int[0|0x0]) <|@ <|@
      nr   -1  <|@ instruction v4|INT = ASSIGN get_global_size(int[1|0x1]) <|@ <|@
      nr   -1  <|@ instruction v5|ULONG = ASSIGN + v2|ULONG long[32|0x20] <|@ <|@
      nr   -1  <|@ instruction v6|ULONG = ASSIGN + v1|ULONG long[32|0x20] <|@ <|@
      nr   -1  <|@ instruction v7|ULONG = ASSIGN + v0|ULONG long[32|0x20] <|@ <|@
      nr   -1  <|@ instruction v8|INT = ASSIGN get_global_id(int[0|0x0]) <|@ <|@
      nr   -1  <|@ instruction v9|INT = ASSIGN get_global_id(int[1|0x1]) <|@ <|@
    end_IR
  end_block
  begin_block
    name "B1"
    from_bci -1
    to_bci -1
    predecessors "B0" "B8" 
    successors "B2" "B9" 
    xhandlers
    flags "llh" 
    loop_index 0
    loop_depth 1
    probability 4611686018427387904
    begin_IR
      LIR
      nr   -1  <|@ instruction [] = LABEL alignment: 0 numbPhis: 0 label: ? <|@ <|@
      nr   -1  <|@ instruction v10|INT = ASSIGN v9|INT <|@ <|@
      nr   -1  <|@ instruction LOOPINIT <|@ <|@
      nr   -1  <|@ instruction LOOPPOST <|@ <|@
      nr   -1  <|@ instruction LOOPCONDITION < v10|INT int[1024|0x400] generateIfBreakStatement: true <|@ <|@
    end_IR
  end_block
  begin_block
    name "B2"
    from_bci -1
    to_bci -1
    predecessors "B1" 
    successors "B3" 
    xhandlers
    flags 
    loop_index 0
    loop_depth 1
    probability 4607182418800017408
    begin_IR
      LIR
      nr   -1  <|@ instruction [] = LABEL alignment: 0 numbPhis: 0 label: ? <|@ <|@
      nr   -1  <|@ instruction v11|INT = ASSIGN << v10|INT int[10|0xa] <|@ <|@
      nr   -1  <|@ instruction v12|INT = ASSIGN + v11|INT int[6|0x6] <|@ <|@
    end_IR
  end_block
  begin_block
    name "B3"
    from_bci -1
    to_bci -1
    predecessors "B2" "B7" 
    successors "B4" "B8" 
    xhandlers
    flags "llh" 
    loop_index 1
    loop_depth 2
    probability 4611686018427387904
    begin_IR
      LIR
      nr   -1  <|@ instruction [] = LABEL alignment: 0 numbPhis: 0 label: ? <|@ <|@
      nr   -1  <|@ instruction v13|INT = ASSIGN v8|INT <|@ <|@
      nr   -1  <|@ instruction LOOPINIT <|@ <|@
      nr   -1  <|@ instruction LOOPPOST <|@ <|@
      nr   -1  <|@ instruction LOOPCONDITION < v13|INT int[1024|0x400] generateIfBreakStatement: true <|@ <|@
    end_IR
  end_block
  begin_block
    name "B4"
    from_bci -1
    to_bci -1
    predecessors "B3" 
    successors "B5" 
    xhandlers
    flags 
    loop_index 1
    loop_depth 2
    probability 4607182418800017408
    begin_IR
      LIR
      nr   -1  <|@ instruction [] = LABEL alignment: 0 numbPhis: 0 label: ? <|@ <|@
      nr   -1  <|@ instruction v14|INT = ASSIGN + v13|INT int[6|0x6] <|@ <|@
    end_IR
  end_block
  begin_block
    name "B5"
    from_bci -1
    to_bci -1
    predecessors "B4" "B6" 
    successors "B6" "B7" 
    xhandlers
    flags "llh" 
    loop_index 2
    loop_depth 3
    probability 4611686018427387904
    begin_IR
      LIR
      nr   -1  <|@ instruction [] = LABEL alignment: 0 numbPhis: 0 label: ? <|@ <|@
      nr   -1  <|@ instruction v15|FLOAT = ASSIGN float[0.0|0x0] <|@ <|@
      nr   -1  <|@ instruction v16|INT = ASSIGN int[0|0x0] <|@ <|@
      nr   -1  <|@ instruction LOOPINIT <|@ <|@
      nr   -1  <|@ instruction LOOPPOST <|@ <|@
      nr   -1  <|@ instruction LOOPCONDITION < v16|INT int[1024|0x400] generateIfBreakStatement: true <|@ <|@
    end_IR
  end_block
  begin_block
    name "B6"
    from_bci -1
    to_bci -1
    predecessors "B5" 
    successors "B5" 
    xhandlers
    flags "lle" 
    loop_index 2
    loop_depth 3
    probability 4607182418800017408
    begin_IR
      LIR
      nr   -1  <|@ instruction [] = LABEL alignment: 0 numbPhis: 0 label: ? <|@ <|@
      nr   -1  <|@ instruction v17|ULONG = LOAD (cast: cast ptr null, address: v7|ULONG, index: null) <|@ <|@
      nr   -1  <|@ instruction v18|ULONG = ASSIGN + v0|ULONG v17|ULONG <|@ <|@
      nr   -1  <|@ instruction v19|INT = ASSIGN + v12|INT v16|INT <|@ <|@
      nr   -1  <|@ instruction v20|LONG = ASSIGN (long)  v19|INT <|@ <|@
      nr   -1  <|@ instruction v21|LONG = ASSIGN << v20|LONG int[2|0x2] <|@ <|@
      nr   -1  <|@ instruction v22|ULONG = ASSIGN + v18|ULONG v21|LONG <|@ <|@
      nr   -1  <|@ instruction v23|FLOAT = LOAD (cast: cast ptr null, address: v22|ULONG, index: null) <|@ <|@
      nr   -1  <|@ instruction v24|ULONG = LOAD (cast: cast ptr null, address: v6|ULONG, index: null) <|@ <|@
      nr   -1  <|@ instruction v25|ULONG = ASSIGN + v1|ULONG v24|ULONG <|@ <|@
      nr   -1  <|@ instruction v26|INT = ASSIGN << v16|INT int[10|0xa] <|@ <|@
      nr   -1  <|@ instruction v27|INT = ASSIGN + v26|INT v14|INT <|@ <|@
      nr   -1  <|@ instruction v28|LONG = ASSIGN (long)  v27|INT <|@ <|@
      nr   -1  <|@ instruction v29|LONG = ASSIGN << v28|LONG int[2|0x2] <|@ <|@
      nr   -1  <|@ instruction v30|ULONG = ASSIGN + v25|ULONG v29|LONG <|@ <|@
      nr   -1  <|@ instruction v31|FLOAT = LOAD (cast: cast ptr null, address: v30|ULONG, index: null) <|@ <|@
      nr   -1  <|@ instruction v32|FLOAT = ASSIGN fma v23|FLOAT v31|FLOAT v15|FLOAT <|@ <|@
      nr   -1  <|@ instruction v33|INT = ASSIGN + v16|INT int[1|0x1] <|@ <|@
      nr   -1  <|@ instruction v15|FLOAT = ASSIGN v32|FLOAT <|@ <|@
      nr   -1  <|@ instruction v16|INT = ASSIGN v33|INT <|@ <|@
    end_IR
  end_block
  begin_block
    name "B7"
    from_bci -1
    to_bci -1
    predecessors "B5" 
    successors "B3" 
    xhandlers
    flags "lle" 
    loop_index 1
    loop_depth 2
    probability 4607182418800017408
    begin_IR
      LIR
      nr   -1  <|@ instruction [] = LABEL alignment: 0 numbPhis: 0 label: ? <|@ <|@
      nr   -1  <|@ instruction v34|ULONG = LOAD (cast: cast ptr null, address: v5|ULONG, index: null) <|@ <|@
      nr   -1  <|@ instruction v35|ULONG = ASSIGN + v2|ULONG v34|ULONG <|@ <|@
      nr   -1  <|@ instruction v36|INT = ASSIGN + v13|INT v12|INT <|@ <|@
      nr   -1  <|@ instruction v37|LONG = ASSIGN (long)  v36|INT <|@ <|@
      nr   -1  <|@ instruction v38|LONG = ASSIGN << v37|LONG int[2|0x2] <|@ <|@
      nr   -1  <|@ instruction v39|ULONG = ASSIGN + v35|ULONG v38|LONG <|@ <|@
      nr   -1  <|@ instruction STORE (rhs: v15|FLOAT, cast: cast ptr null, address: v39|ULONG, index: null) <|@ <|@
      nr   -1  <|@ instruction v40|INT = ASSIGN + v3|INT v13|INT <|@ <|@
      nr   -1  <|@ instruction v13|INT = ASSIGN v40|INT <|@ <|@
    end_IR
  end_block
  begin_block
    name "B8"
    from_bci -1
    to_bci -1
    predecessors "B3" 
    successors "B1" 
    xhandlers
    flags "lle" 
    loop_index 0
    loop_depth 1
    probability 4607182418800017408
    begin_IR
      LIR
      nr   -1  <|@ instruction [] = LABEL alignment: 0 numbPhis: 0 label: ? <|@ <|@
      nr   -1  <|@ instruction v41|INT = ASSIGN + v4|INT v10|INT <|@ <|@
      nr   -1  <|@ instruction v10|INT = ASSIGN v41|INT <|@ <|@
    end_IR
  end_block
  begin_block
    name "B9"
    from_bci -1
    to_bci -1
    predecessors "B1" 
    successors 
    xhandlers
    flags 
    probability 4607182418800017408
    begin_IR
      LIR
      nr   -1  <|@ instruction [] = LABEL alignment: 0 numbPhis: 0 label: ? <|@ <|@
      nr   -1  <|@ instruction EXPR return <|@ <|@
    end_IR
  end_block
end_cfg
begin_bytecodes
     0: iconst_0      
     1: istore_3      
     2: iload_3       
     3: sipush        1024
     6: if_icmpge     82
     9: iconst_0      
    10: istore        4
    12: iload         4
    14: sipush        1024
    17: if_icmpge     76
    20: fconst_0      
    21: fstore        5
    23: iconst_0      
    24: istore        6
    26: iload         6
    28: sipush        1024
    31: if_icmpge     61
    34: fload         5
    36: aload_0       
    37: iload_3       
    38: iload         6
    40: invokevirtual #1          // uk.ac.manchester.tornado.api.types.matrix.Matrix2DFloat.get:(int, int)float
    43: aload_1       
    44: iload         6
    46: iload         4
    48: invokevirtual #1          // uk.ac.manchester.tornado.api.types.matrix.Matrix2DFloat.get:(int, int)float
    51: fmul          
    52: fadd          
    53: fstore        5
    55: iinc          
    58: goto          26
    61: aload_2       
    62: iload_3       
    63: iload         4
    65: fload         5
    67: invokevirtual #2          // uk.ac.manchester.tornado.api.types.matrix.Matrix2DFloat.set:(int, int, float)void
    70: iinc          
    73: goto          12
    76: iinc          
    79: goto          2
    82: return        
   <|@
end_bytecodes
begin_cfg
  name "After LIR generation"
  begin_block
    name "B0"
    from_bci -1
    to_bci -1
    predecessors 
    successors "B1" 
    xhandlers
    flags 
    probability 4607182418800017408
    begin_IR
      LIR
      nr   -1  <|@ instruction [] = LABEL alignment: 0 numbPhis: 0 label: ? <|@ <|@
      nr   -1  <|@ instruction v0|ULONG = ASSIGN (ulong) A <|@ <|@
      nr   -1  <|@ instruction v1|ULONG = ASSIGN (ulong) B <|@ <|@
      nr   -1  <|@ instruction v2|ULONG = ASSIGN (ulong) C <|@ <|@
      nr   -1  <|@ instruction v3|INT = ASSIGN get_global_size(int[0|0x0]) <|@ <|@
      nr   -1  <|@ instruction v4|INT = ASSIGN get_global_size(int[1|0x1]) <|@ <|@
      nr   -1  <|@ instruction v5|ULONG = ASSIGN + v2|ULONG long[32|0x20] <|@ <|@
      nr   -1  <|@ instruction v6|ULONG = ASSIGN + v1|ULONG long[32|0x20] <|@ <|@
      nr   -1  <|@ instruction v7|ULONG = ASSIGN + v0|ULONG long[32|0x20] <|@ <|@
      nr   -1  <|@ instruction v8|INT = ASSIGN get_global_id(int[0|0x0]) <|@ <|@
      nr   -1  <|@ instruction v9|INT = ASSIGN get_global_id(int[1|0x1]) <|@ <|@
    end_IR
  end_block
  begin_block
    name "B1"
    from_bci -1
    to_bci -1
    predecessors "B0" "B8" 
    successors "B2" "B9" 
    xhandlers
    flags "llh" 
    loop_index 0
    loop_depth 1
    probability 4611686018427387904
    begin_IR
      LIR
      nr   -1  <|@ instruction [] = LABEL alignment: 0 numbPhis: 0 label: ? <|@ <|@
      nr   -1  <|@ instruction v10|INT = ASSIGN v9|INT <|@ <|@
      nr   -1  <|@ instruction LOOPINIT <|@ <|@
      nr   -1  <|@ instruction LOOPPOST <|@ <|@
      nr   -1  <|@ instruction LOOPCONDITION < v10|INT int[1024|0x400] generateIfBreakStatement: true <|@ <|@
    end_IR
  end_block
  begin_block
    name "B2"
    from_bci -1
    to_bci -1
    predecessors "B1" 
    successors "B3" 
    xhandlers
    flags 
    loop_index 0
    loop_depth 1
    probability 4607182418800017408
    begin_IR
      LIR
      nr   -1  <|@ instruction [] = LABEL alignment: 0 numbPhis: 0 label: ? <|@ <|@
      nr   -1  <|@ instruction v11|INT = ASSIGN << v10|INT int[10|0xa] <|@ <|@
      nr   -1  <|@ instruction v12|INT = ASSIGN + v11|INT int[6|0x6] <|@ <|@
    end_IR
  end_block
  begin_block
    name "B3"
    from_bci -1
    to_bci -1
    predecessors "B2" "B7" 
    successors "B4" "B8" 
    xhandlers
    flags "llh" 
    loop_index 1
    loop_depth 2
    probability 4611686018427387904
    begin_IR
      LIR
      nr   -1  <|@ instruction [] = LABEL alignment: 0 numbPhis: 0 label: ? <|@ <|@
      nr   -1  <|@ instruction v13|INT = ASSIGN v8|INT <|@ <|@
      nr   -1  <|@ instruction LOOPINIT <|@ <|@
      nr   -1  <|@ instruction LOOPPOST <|@ <|@
      nr   -1  <|@ instruction LOOPCONDITION < v13|INT int[1024|0x400] generateIfBreakStatement: true <|@ <|@
    end_IR
  end_block
  begin_block
    name "B4"
    from_bci -1
    to_bci -1
    predecessors "B3" 
    successors "B5" 
    xhandlers
    flags 
    loop_index 1
    loop_depth 2
    probability 4607182418800017408
    begin_IR
      LIR
      nr   -1  <|@ instruction [] = LABEL alignment: 0 numbPhis: 0 label: ? <|@ <|@
      nr   -1  <|@ instruction v14|INT = ASSIGN + v13|INT int[6|0x6] <|@ <|@
    end_IR
  end_block
  begin_block
    name "B5"
    from_bci -1
    to_bci -1
    predecessors "B4" "B6" 
    successors "B6" "B7" 
    xhandlers
    flags "llh" 
    loop_index 2
    loop_depth 3
    probability 4611686018427387904
    begin_IR
      LIR
      nr   -1  <|@ instruction [] = LABEL alignment: 0 numbPhis: 0 label: ? <|@ <|@
      nr   -1  <|@ instruction v15|FLOAT = ASSIGN float[0.0|0x0] <|@ <|@
      nr   -1  <|@ instruction v16|INT = ASSIGN int[0|0x0] <|@ <|@
      nr   -1  <|@ instruction LOOPINIT <|@ <|@
      nr   -1  <|@ instruction LOOPPOST <|@ <|@
      nr   -1  <|@ instruction LOOPCONDITION < v16|INT int[1024|0x400] generateIfBreakStatement: true <|@ <|@
    end_IR
  end_block
  begin_block
    name "B6"
    from_bci -1
    to_bci -1
    predecessors "B5" 
    successors "B5" 
    xhandlers
    flags "lle" 
    loop_index 2
    loop_depth 3
    probability 4607182418800017408
    begin_IR
      LIR
      nr   -1  <|@ instruction [] = LABEL alignment: 0 numbPhis: 0 label: ? <|@ <|@
      nr   -1  <|@ instruction v17|ULONG = LOAD (cast: cast ptr null, address: v7|ULONG, index: null) <|@ <|@
      nr   -1  <|@ instruction v18|ULONG = ASSIGN + v0|ULONG v17|ULONG <|@ <|@
      nr   -1  <|@ instruction v19|INT = ASSIGN + v12|INT v16|INT <|@ <|@
      nr   -1  <|@ instruction v20|LONG = ASSIGN (long)  v19|INT <|@ <|@
      nr   -1  <|@ instruction v21|LONG = ASSIGN << v20|LONG int[2|0x2] <|@ <|@
      nr   -1  <|@ instruction v22|ULONG = ASSIGN + v18|ULONG v21|LONG <|@ <|@
      nr   -1  <|@ instruction v23|FLOAT = LOAD (cast: cast ptr null, address: v22|ULONG, index: null) <|@ <|@
      nr   -1  <|@ instruction v24|ULONG = LOAD (cast: cast ptr null, address: v6|ULONG, index: null) <|@ <|@
      nr   -1  <|@ instruction v25|ULONG = ASSIGN + v1|ULONG v24|ULONG <|@ <|@
      nr   -1  <|@ instruction v26|INT = ASSIGN << v16|INT int[10|0xa] <|@ <|@
      nr   -1  <|@ instruction v27|INT = ASSIGN + v26|INT v14|INT <|@ <|@
      nr   -1  <|@ instruction v28|LONG = ASSIGN (long)  v27|INT <|@ <|@
      nr   -1  <|@ instruction v29|LONG = ASSIGN << v28|LONG int[2|0x2] <|@ <|@
      nr   -1  <|@ instruction v30|ULONG = ASSIGN + v25|ULONG v29|LONG <|@ <|@
      nr   -1  <|@ instruction v31|FLOAT = LOAD (cast: cast ptr null, address: v30|ULONG, index: null) <|@ <|@
      nr   -1  <|@ instruction v32|FLOAT = ASSIGN fma v23|FLOAT v31|FLOAT v15|FLOAT <|@ <|@
      nr   -1  <|@ instruction v33|INT = ASSIGN + v16|INT int[1|0x1] <|@ <|@
      nr   -1  <|@ instruction v15|FLOAT = ASSIGN v32|FLOAT <|@ <|@
      nr   -1  <|@ instruction v16|INT = ASSIGN v33|INT <|@ <|@
    end_IR
  end_block
  begin_block
    name "B7"
    from_bci -1
    to_bci -1
    predecessors "B5" 
    successors "B3" 
    xhandlers
    flags "lle" 
    loop_index 1
    loop_depth 2
    probability 4607182418800017408
    begin_IR
      LIR
      nr   -1  <|@ instruction [] = LABEL alignment: 0 numbPhis: 0 label: ? <|@ <|@
      nr   -1  <|@ instruction v34|ULONG = LOAD (cast: cast ptr null, address: v5|ULONG, index: null) <|@ <|@
      nr   -1  <|@ instruction v35|ULONG = ASSIGN + v2|ULONG v34|ULONG <|@ <|@
      nr   -1  <|@ instruction v36|INT = ASSIGN + v13|INT v12|INT <|@ <|@
      nr   -1  <|@ instruction v37|LONG = ASSIGN (long)  v36|INT <|@ <|@
      nr   -1  <|@ instruction v38|LONG = ASSIGN << v37|LONG int[2|0x2] <|@ <|@
      nr   -1  <|@ instruction v39|ULONG = ASSIGN + v35|ULONG v38|LONG <|@ <|@
      nr   -1  <|@ instruction STORE (rhs: v15|FLOAT, cast: cast ptr null, address: v39|ULONG, index: null) <|@ <|@
      nr   -1  <|@ instruction v40|INT = ASSIGN + v3|INT v13|INT <|@ <|@
      nr   -1  <|@ instruction v13|INT = ASSIGN v40|INT <|@ <|@
    end_IR
  end_block
  begin_block
    name "B8"
    from_bci -1
    to_bci -1
    predecessors "B3" 
    successors "B1" 
    xhandlers
    flags "lle" 
    loop_index 0
    loop_depth 1
    probability 4607182418800017408
    begin_IR
      LIR
      nr   -1  <|@ instruction [] = LABEL alignment: 0 numbPhis: 0 label: ? <|@ <|@
      nr   -1  <|@ instruction v41|INT = ASSIGN + v4|INT v10|INT <|@ <|@
      nr   -1  <|@ instruction v10|INT = ASSIGN v41|INT <|@ <|@
    end_IR
  end_block
  begin_block
    name "B9"
    from_bci -1
    to_bci -1
    predecessors "B1" 
    successors 
    xhandlers
    flags 
    probability 4607182418800017408
    begin_IR
      LIR
      nr   -1  <|@ instruction [] = LABEL alignment: 0 numbPhis: 0 label: ? <|@ <|@
      nr   -1  <|@ instruction EXPR return <|@ <|@
    end_IR
  end_block
end_cfg
begin_bytecodes
     0: iconst_0      
     1: istore_3      
     2: iload_3       
     3: sipush        1024
     6: if_icmpge     82
     9: iconst_0      
    10: istore        4
    12: iload         4
    14: sipush        1024
    17: if_icmpge     76
    20: fconst_0      
    21: fstore        5
    23: iconst_0      
    24: istore        6
    26: iload         6
    28: sipush        1024
    31: if_icmpge     61
    34: fload         5
    36: aload_0       
    37: iload_3       
    38: iload         6
    40: invokevirtual #1          // uk.ac.manchester.tornado.api.types.matrix.Matrix2DFloat.get:(int, int)float
    43: aload_1       
    44: iload         6
    46: iload         4
    48: invokevirtual #1          // uk.ac.manchester.tornado.api.types.matrix.Matrix2DFloat.get:(int, int)float
    51: fmul          
    52: fadd          
    53: fstore        5
    55: iinc          
    58: goto          26
    61: aload_2       
    62: iload_3       
    63: iload         4
    65: fload         5
    67: invokevirtual #2          // uk.ac.manchester.tornado.api.types.matrix.Matrix2DFloat.set:(int, int, float)void
    70: iinc          
    73: goto          12
    76: iinc          
    79: goto          2
    82: return        
   <|@
end_bytecodes
begin_cfg
  name "After SaveCalleeSaveRegisters"
  begin_block
    name "B0"
    from_bci -1
    to_bci -1
    predecessors 
    successors "B1" 
    xhandlers
    flags 
    probability 4607182418800017408
    begin_IR
      LIR
      nr   -1  <|@ instruction [] = LABEL alignment: 0 numbPhis: 0 label: ? <|@ <|@
      nr   -1  <|@ instruction v0|ULONG = ASSIGN (ulong) A <|@ <|@
      nr   -1  <|@ instruction v1|ULONG = ASSIGN (ulong) B <|@ <|@
      nr   -1  <|@ instruction v2|ULONG = ASSIGN (ulong) C <|@ <|@
      nr   -1  <|@ instruction v3|INT = ASSIGN get_global_size(int[0|0x0]) <|@ <|@
      nr   -1  <|@ instruction v4|INT = ASSIGN get_global_size(int[1|0x1]) <|@ <|@
      nr   -1  <|@ instruction v5|ULONG = ASSIGN + v2|ULONG long[32|0x20] <|@ <|@
      nr   -1  <|@ instruction v6|ULONG = ASSIGN + v1|ULONG long[32|0x20] <|@ <|@
      nr   -1  <|@ instruction v7|ULONG = ASSIGN + v0|ULONG long[32|0x20] <|@ <|@
      nr   -1  <|@ instruction v8|INT = ASSIGN get_global_id(int[0|0x0]) <|@ <|@
      nr   -1  <|@ instruction v9|INT = ASSIGN get_global_id(int[1|0x1]) <|@ <|@
    end_IR
  end_block
  begin_block
    name "B1"
    from_bci -1
    to_bci -1
    predecessors "B0" "B8" 
    successors "B2" "B9" 
    xhandlers
    flags "llh" 
    loop_index 0
    loop_depth 1
    probability 4611686018427387904
    begin_IR
      LIR
      nr   -1  <|@ instruction [] = LABEL alignment: 0 numbPhis: 0 label: ? <|@ <|@
      nr   -1  <|@ instruction v10|INT = ASSIGN v9|INT <|@ <|@
      nr   -1  <|@ instruction LOOPINIT <|@ <|@
      nr   -1  <|@ instruction LOOPPOST <|@ <|@
      nr   -1  <|@ instruction LOOPCONDITION < v10|INT int[1024|0x400] generateIfBreakStatement: true <|@ <|@
    end_IR
  end_block
  begin_block
    name "B2"
    from_bci -1
    to_bci -1
    predecessors "B1" 
    successors "B3" 
    xhandlers
    flags 
    loop_index 0
    loop_depth 1
    probability 4607182418800017408
    begin_IR
      LIR
      nr   -1  <|@ instruction [] = LABEL alignment: 0 numbPhis: 0 label: ? <|@ <|@
      nr   -1  <|@ instruction v11|INT = ASSIGN << v10|INT int[10|0xa] <|@ <|@
      nr   -1  <|@ instruction v12|INT = ASSIGN + v11|INT int[6|0x6] <|@ <|@
    end_IR
  end_block
  begin_block
    name "B3"
    from_bci -1
    to_bci -1
    predecessors "B2" "B7" 
    successors "B4" "B8" 
    xhandlers
    flags "llh" 
    loop_index 1
    loop_depth 2
    probability 4611686018427387904
    begin_IR
      LIR
      nr   -1  <|@ instruction [] = LABEL alignment: 0 numbPhis: 0 label: ? <|@ <|@
      nr   -1  <|@ instruction v13|INT = ASSIGN v8|INT <|@ <|@
      nr   -1  <|@ instruction LOOPINIT <|@ <|@
      nr   -1  <|@ instruction LOOPPOST <|@ <|@
      nr   -1  <|@ instruction LOOPCONDITION < v13|INT int[1024|0x400] generateIfBreakStatement: true <|@ <|@
    end_IR
  end_block
  begin_block
    name "B4"
    from_bci -1
    to_bci -1
    predecessors "B3" 
    successors "B5" 
    xhandlers
    flags 
    loop_index 1
    loop_depth 2
    probability 4607182418800017408
    begin_IR
      LIR
      nr   -1  <|@ instruction [] = LABEL alignment: 0 numbPhis: 0 label: ? <|@ <|@
      nr   -1  <|@ instruction v14|INT = ASSIGN + v13|INT int[6|0x6] <|@ <|@
    end_IR
  end_block
  begin_block
    name "B5"
    from_bci -1
    to_bci -1
    predecessors "B4" "B6" 
    successors "B6" "B7" 
    xhandlers
    flags "llh" 
    loop_index 2
    loop_depth 3
    probability 4611686018427387904
    begin_IR
      LIR
      nr   -1  <|@ instruction [] = LABEL alignment: 0 numbPhis: 0 label: ? <|@ <|@
      nr   -1  <|@ instruction v15|FLOAT = ASSIGN float[0.0|0x0] <|@ <|@
      nr   -1  <|@ instruction v16|INT = ASSIGN int[0|0x0] <|@ <|@
      nr   -1  <|@ instruction LOOPINIT <|@ <|@
      nr   -1  <|@ instruction LOOPPOST <|@ <|@
      nr   -1  <|@ instruction LOOPCONDITION < v16|INT int[1024|0x400] generateIfBreakStatement: true <|@ <|@
    end_IR
  end_block
  begin_block
    name "B6"
    from_bci -1
    to_bci -1
    predecessors "B5" 
    successors "B5" 
    xhandlers
    flags "lle" 
    loop_index 2
    loop_depth 3
    probability 4607182418800017408
    begin_IR
      LIR
      nr   -1  <|@ instruction [] = LABEL alignment: 0 numbPhis: 0 label: ? <|@ <|@
      nr   -1  <|@ instruction v17|ULONG = LOAD (cast: cast ptr null, address: v7|ULONG, index: null) <|@ <|@
      nr   -1  <|@ instruction v18|ULONG = ASSIGN + v0|ULONG v17|ULONG <|@ <|@
      nr   -1  <|@ instruction v19|INT = ASSIGN + v12|INT v16|INT <|@ <|@
      nr   -1  <|@ instruction v20|LONG = ASSIGN (long)  v19|INT <|@ <|@
      nr   -1  <|@ instruction v21|LONG = ASSIGN << v20|LONG int[2|0x2] <|@ <|@
      nr   -1  <|@ instruction v22|ULONG = ASSIGN + v18|ULONG v21|LONG <|@ <|@
      nr   -1  <|@ instruction v23|FLOAT = LOAD (cast: cast ptr null, address: v22|ULONG, index: null) <|@ <|@
      nr   -1  <|@ instruction v24|ULONG = LOAD (cast: cast ptr null, address: v6|ULONG, index: null) <|@ <|@
      nr   -1  <|@ instruction v25|ULONG = ASSIGN + v1|ULONG v24|ULONG <|@ <|@
      nr   -1  <|@ instruction v26|INT = ASSIGN << v16|INT int[10|0xa] <|@ <|@
      nr   -1  <|@ instruction v27|INT = ASSIGN + v26|INT v14|INT <|@ <|@
      nr   -1  <|@ instruction v28|LONG = ASSIGN (long)  v27|INT <|@ <|@
      nr   -1  <|@ instruction v29|LONG = ASSIGN << v28|LONG int[2|0x2] <|@ <|@
      nr   -1  <|@ instruction v30|ULONG = ASSIGN + v25|ULONG v29|LONG <|@ <|@
      nr   -1  <|@ instruction v31|FLOAT = LOAD (cast: cast ptr null, address: v30|ULONG, index: null) <|@ <|@
      nr   -1  <|@ instruction v32|FLOAT = ASSIGN fma v23|FLOAT v31|FLOAT v15|FLOAT <|@ <|@
      nr   -1  <|@ instruction v33|INT = ASSIGN + v16|INT int[1|0x1] <|@ <|@
      nr   -1  <|@ instruction v15|FLOAT = ASSIGN v32|FLOAT <|@ <|@
      nr   -1  <|@ instruction v16|INT = ASSIGN v33|INT <|@ <|@
    end_IR
  end_block
  begin_block
    name "B7"
    from_bci -1
    to_bci -1
    predecessors "B5" 
    successors "B3" 
    xhandlers
    flags "lle" 
    loop_index 1
    loop_depth 2
    probability 4607182418800017408
    begin_IR
      LIR
      nr   -1  <|@ instruction [] = LABEL alignment: 0 numbPhis: 0 label: ? <|@ <|@
      nr   -1  <|@ instruction v34|ULONG = LOAD (cast: cast ptr null, address: v5|ULONG, index: null) <|@ <|@
      nr   -1  <|@ instruction v35|ULONG = ASSIGN + v2|ULONG v34|ULONG <|@ <|@
      nr   -1  <|@ instruction v36|INT = ASSIGN + v13|INT v12|INT <|@ <|@
      nr   -1  <|@ instruction v37|LONG = ASSIGN (long)  v36|INT <|@ <|@
      nr   -1  <|@ instruction v38|LONG = ASSIGN << v37|LONG int[2|0x2] <|@ <|@
      nr   -1  <|@ instruction v39|ULONG = ASSIGN + v35|ULONG v38|LONG <|@ <|@
      nr   -1  <|@ instruction STORE (rhs: v15|FLOAT, cast: cast ptr null, address: v39|ULONG, index: null) <|@ <|@
      nr   -1  <|@ instruction v40|INT = ASSIGN + v3|INT v13|INT <|@ <|@
      nr   -1  <|@ instruction v13|INT = ASSIGN v40|INT <|@ <|@
    end_IR
  end_block
  begin_block
    name "B8"
    from_bci -1
    to_bci -1
    predecessors "B3" 
    successors "B1" 
    xhandlers
    flags "lle" 
    loop_index 0
    loop_depth 1
    probability 4607182418800017408
    begin_IR
      LIR
      nr   -1  <|@ instruction [] = LABEL alignment: 0 numbPhis: 0 label: ? <|@ <|@
      nr   -1  <|@ instruction v41|INT = ASSIGN + v4|INT v10|INT <|@ <|@
      nr   -1  <|@ instruction v10|INT = ASSIGN v41|INT <|@ <|@
    end_IR
  end_block
  begin_block
    name "B9"
    from_bci -1
    to_bci -1
    predecessors "B1" 
    successors 
    xhandlers
    flags 
    probability 4607182418800017408
    begin_IR
      LIR
      nr   -1  <|@ instruction [] = LABEL alignment: 0 numbPhis: 0 label: ? <|@ <|@
      nr   -1  <|@ instruction EXPR return <|@ <|@
    end_IR
  end_block
end_cfg
begin_bytecodes
     0: iconst_0      
     1: istore_3      
     2: iload_3       
     3: sipush        1024
     6: if_icmpge     82
     9: iconst_0      
    10: istore        4
    12: iload         4
    14: sipush        1024
    17: if_icmpge     76
    20: fconst_0      
    21: fstore        5
    23: iconst_0      
    24: istore        6
    26: iload         6
    28: sipush        1024
    31: if_icmpge     61
    34: fload         5
    36: aload_0       
    37: iload_3       
    38: iload         6
    40: invokevirtual #1          // uk.ac.manchester.tornado.api.types.matrix.Matrix2DFloat.get:(int, int)float
    43: aload_1       
    44: iload         6
    46: iload         4
    48: invokevirtual #1          // uk.ac.manchester.tornado.api.types.matrix.Matrix2DFloat.get:(int, int)float
    51: fmul          
    52: fadd          
    53: fstore        5
    55: iinc          
    58: goto          26
    61: aload_2       
    62: iload_3       
    63: iload         4
    65: fload         5
    67: invokevirtual #2          // uk.ac.manchester.tornado.api.types.matrix.Matrix2DFloat.set:(int, int, float)void
    70: iinc          
    73: goto          12
    76: iinc          
    79: goto          2
    82: return        
   <|@
end_bytecodes
begin_cfg
  name "Before code generation"
  begin_block
    name "B0"
    from_bci -1
    to_bci -1
    predecessors 
    successors "B1" 
    xhandlers
    flags 
    probability 4607182418800017408
    begin_IR
      LIR
      nr   -1  <|@ instruction [] = LABEL alignment: 0 numbPhis: 0 label: ? <|@ <|@
      nr   -1  <|@ instruction v0|ULONG = ASSIGN (ulong) A <|@ <|@
      nr   -1  <|@ instruction v1|ULONG = ASSIGN (ulong) B <|@ <|@
      nr   -1  <|@ instruction v2|ULONG = ASSIGN (ulong) C <|@ <|@
      nr   -1  <|@ instruction v3|INT = ASSIGN get_global_size(int[0|0x0]) <|@ <|@
      nr   -1  <|@ instruction v4|INT = ASSIGN get_global_size(int[1|0x1]) <|@ <|@
      nr   -1  <|@ instruction v5|ULONG = ASSIGN + v2|ULONG long[32|0x20] <|@ <|@
      nr   -1  <|@ instruction v6|ULONG = ASSIGN + v1|ULONG long[32|0x20] <|@ <|@
      nr   -1  <|@ instruction v7|ULONG = ASSIGN + v0|ULONG long[32|0x20] <|@ <|@
      nr   -1  <|@ instruction v8|INT = ASSIGN get_global_id(int[0|0x0]) <|@ <|@
      nr   -1  <|@ instruction v9|INT = ASSIGN get_global_id(int[1|0x1]) <|@ <|@
    end_IR
  end_block
  begin_block
    name "B1"
    from_bci -1
    to_bci -1
    predecessors "B0" "B8" 
    successors "B2" "B9" 
    xhandlers
    flags "llh" 
    loop_index 0
    loop_depth 1
    probability 4611686018427387904
    begin_IR
      LIR
      nr   -1  <|@ instruction [] = LABEL alignment: 0 numbPhis: 0 label: ? <|@ <|@
      nr   -1  <|@ instruction v10|INT = ASSIGN v9|INT <|@ <|@
      nr   -1  <|@ instruction LOOPINIT <|@ <|@
      nr   -1  <|@ instruction LOOPPOST <|@ <|@
      nr   -1  <|@ instruction LOOPCONDITION < v10|INT int[1024|0x400] generateIfBreakStatement: true <|@ <|@
    end_IR
  end_block
  begin_block
    name "B2"
    from_bci -1
    to_bci -1
    predecessors "B1" 
    successors "B3" 
    xhandlers
    flags 
    loop_index 0
    loop_depth 1
    probability 4607182418800017408
    begin_IR
      LIR
      nr   -1  <|@ instruction [] = LABEL alignment: 0 numbPhis: 0 label: ? <|@ <|@
      nr   -1  <|@ instruction v11|INT = ASSIGN << v10|INT int[10|0xa] <|@ <|@
      nr   -1  <|@ instruction v12|INT = ASSIGN + v11|INT int[6|0x6] <|@ <|@
    end_IR
  end_block
  begin_block
    name "B3"
    from_bci -1
    to_bci -1
    predecessors "B2" "B7" 
    successors "B4" "B8" 
    xhandlers
    flags "llh" 
    loop_index 1
    loop_depth 2
    probability 4611686018427387904
    begin_IR
      LIR
      nr   -1  <|@ instruction [] = LABEL alignment: 0 numbPhis: 0 label: ? <|@ <|@
      nr   -1  <|@ instruction v13|INT = ASSIGN v8|INT <|@ <|@
      nr   -1  <|@ instruction LOOPINIT <|@ <|@
      nr   -1  <|@ instruction LOOPPOST <|@ <|@
      nr   -1  <|@ instruction LOOPCONDITION < v13|INT int[1024|0x400] generateIfBreakStatement: true <|@ <|@
    end_IR
  end_block
  begin_block
    name "B4"
    from_bci -1
    to_bci -1
    predecessors "B3" 
    successors "B5" 
    xhandlers
    flags 
    loop_index 1
    loop_depth 2
    probability 4607182418800017408
    begin_IR
      LIR
      nr   -1  <|@ instruction [] = LABEL alignment: 0 numbPhis: 0 label: ? <|@ <|@
      nr   -1  <|@ instruction v14|INT = ASSIGN + v13|INT int[6|0x6] <|@ <|@
    end_IR
  end_block
  begin_block
    name "B5"
    from_bci -1
    to_bci -1
    predecessors "B4" "B6" 
    successors "B6" "B7" 
    xhandlers
    flags "llh" 
    loop_index 2
    loop_depth 3
    probability 4611686018427387904
    begin_IR
      LIR
      nr   -1  <|@ instruction [] = LABEL alignment: 0 numbPhis: 0 label: ? <|@ <|@
      nr   -1  <|@ instruction v15|FLOAT = ASSIGN float[0.0|0x0] <|@ <|@
      nr   -1  <|@ instruction v16|INT = ASSIGN int[0|0x0] <|@ <|@
      nr   -1  <|@ instruction LOOPINIT <|@ <|@
      nr   -1  <|@ instruction LOOPPOST <|@ <|@
      nr   -1  <|@ instruction LOOPCONDITION < v16|INT int[1024|0x400] generateIfBreakStatement: true <|@ <|@
    end_IR
  end_block
  begin_block
    name "B6"
    from_bci -1
    to_bci -1
    predecessors "B5" 
    successors "B5" 
    xhandlers
    flags "lle" 
    loop_index 2
    loop_depth 3
    probability 4607182418800017408
    begin_IR
      LIR
      nr   -1  <|@ instruction [] = LABEL alignment: 0 numbPhis: 0 label: ? <|@ <|@
      nr   -1  <|@ instruction v17|ULONG = LOAD (cast: cast ptr null, address: v7|ULONG, index: null) <|@ <|@
      nr   -1  <|@ instruction v18|ULONG = ASSIGN + v0|ULONG v17|ULONG <|@ <|@
      nr   -1  <|@ instruction v19|INT = ASSIGN + v12|INT v16|INT <|@ <|@
      nr   -1  <|@ instruction v20|LONG = ASSIGN (long)  v19|INT <|@ <|@
      nr   -1  <|@ instruction v21|LONG = ASSIGN << v20|LONG int[2|0x2] <|@ <|@
      nr   -1  <|@ instruction v22|ULONG = ASSIGN + v18|ULONG v21|LONG <|@ <|@
      nr   -1  <|@ instruction v23|FLOAT = LOAD (cast: cast ptr null, address: v22|ULONG, index: null) <|@ <|@
      nr   -1  <|@ instruction v24|ULONG = LOAD (cast: cast ptr null, address: v6|ULONG, index: null) <|@ <|@
      nr   -1  <|@ instruction v25|ULONG = ASSIGN + v1|ULONG v24|ULONG <|@ <|@
      nr   -1  <|@ instruction v26|INT = ASSIGN << v16|INT int[10|0xa] <|@ <|@
      nr   -1  <|@ instruction v27|INT = ASSIGN + v26|INT v14|INT <|@ <|@
      nr   -1  <|@ instruction v28|LONG = ASSIGN (long)  v27|INT <|@ <|@
      nr   -1  <|@ instruction v29|LONG = ASSIGN << v28|LONG int[2|0x2] <|@ <|@
      nr   -1  <|@ instruction v30|ULONG = ASSIGN + v25|ULONG v29|LONG <|@ <|@
      nr   -1  <|@ instruction v31|FLOAT = LOAD (cast: cast ptr null, address: v30|ULONG, index: null) <|@ <|@
      nr   -1  <|@ instruction v32|FLOAT = ASSIGN fma v23|FLOAT v31|FLOAT v15|FLOAT <|@ <|@
      nr   -1  <|@ instruction v33|INT = ASSIGN + v16|INT int[1|0x1] <|@ <|@
      nr   -1  <|@ instruction v15|FLOAT = ASSIGN v32|FLOAT <|@ <|@
      nr   -1  <|@ instruction v16|INT = ASSIGN v33|INT <|@ <|@
    end_IR
  end_block
  begin_block
    name "B7"
    from_bci -1
    to_bci -1
    predecessors "B5" 
    successors "B3" 
    xhandlers
    flags "lle" 
    loop_index 1
    loop_depth 2
    probability 4607182418800017408
    begin_IR
      LIR
      nr   -1  <|@ instruction [] = LABEL alignment: 0 numbPhis: 0 label: ? <|@ <|@
      nr   -1  <|@ instruction v34|ULONG = LOAD (cast: cast ptr null, address: v5|ULONG, index: null) <|@ <|@
      nr   -1  <|@ instruction v35|ULONG = ASSIGN + v2|ULONG v34|ULONG <|@ <|@
      nr   -1  <|@ instruction v36|INT = ASSIGN + v13|INT v12|INT <|@ <|@
      nr   -1  <|@ instruction v37|LONG = ASSIGN (long)  v36|INT <|@ <|@
      nr   -1  <|@ instruction v38|LONG = ASSIGN << v37|LONG int[2|0x2] <|@ <|@
      nr   -1  <|@ instruction v39|ULONG = ASSIGN + v35|ULONG v38|LONG <|@ <|@
      nr   -1  <|@ instruction STORE (rhs: v15|FLOAT, cast: cast ptr null, address: v39|ULONG, index: null) <|@ <|@
      nr   -1  <|@ instruction v40|INT = ASSIGN + v3|INT v13|INT <|@ <|@
      nr   -1  <|@ instruction v13|INT = ASSIGN v40|INT <|@ <|@
    end_IR
  end_block
  begin_block
    name "B8"
    from_bci -1
    to_bci -1
    predecessors "B3" 
    successors "B1" 
    xhandlers
    flags "lle" 
    loop_index 0
    loop_depth 1
    probability 4607182418800017408
    begin_IR
      LIR
      nr   -1  <|@ instruction [] = LABEL alignment: 0 numbPhis: 0 label: ? <|@ <|@
      nr   -1  <|@ instruction v41|INT = ASSIGN + v4|INT v10|INT <|@ <|@
      nr   -1  <|@ instruction v10|INT = ASSIGN v41|INT <|@ <|@
    end_IR
  end_block
  begin_block
    name "B9"
    from_bci -1
    to_bci -1
    predecessors "B1" 
    successors 
    xhandlers
    flags 
    probability 4607182418800017408
    begin_IR
      LIR
      nr   -1  <|@ instruction [] = LABEL alignment: 0 numbPhis: 0 label: ? <|@ <|@
      nr   -1  <|@ instruction EXPR return <|@ <|@
    end_IR
  end_block
end_cfg
begin_bytecodes
     0: iconst_0      
     1: istore_3      
     2: iload_3       
     3: sipush        1024
     6: if_icmpge     82
     9: iconst_0      
    10: istore        4
    12: iload         4
    14: sipush        1024
    17: if_icmpge     76
    20: fconst_0      
    21: fstore        5
    23: iconst_0      
    24: istore        6
    26: iload         6
    28: sipush        1024
    31: if_icmpge     61
    34: fload         5
    36: aload_0       
    37: iload_3       
    38: iload         6
    40: invokevirtual #1          // uk.ac.manchester.tornado.api.types.matrix.Matrix2DFloat.get:(int, int)float
    43: aload_1       
    44: iload         6
    46: iload         4
    48: invokevirtual #1          // uk.ac.manchester.tornado.api.types.matrix.Matrix2DFloat.get:(int, int)float
    51: fmul          
    52: fadd          
    53: fstore        5
    55: iinc          
    58: goto          26
    61: aload_2       
    62: iload_3       
    63: iload         4
    65: fload         5
    67: invokevirtual #2          // uk.ac.manchester.tornado.api.types.matrix.Matrix2DFloat.set:(int, int, float)void
    70: iinc          
    73: goto          12
    76: iinc          
    79: goto          2
    82: return        
   <|@
end_bytecodes
begin_cfg
  name "After code generation"
end_cfg
begin_nmethod
  <<<HexCodeFile
  Platform Tornado OpenCL 64  <||@
  HexCode 0 23707261676d61204f50454e434c20455854454e53494f4e20636c5f6b68725f66703634203a20656e61626c6520200a23707261676d61204f50454e434c20455854454e53494f4e20636c5f6b68725f66703136203a20656e61626c6520200a23707261676d61204f50454e434c20455854454e53494f4e20636c5f6b68725f696e7436345f626173655f61746f6d696373203a20656e61626c6520200a5f5f6b65726e656c20766f6964204d756c7469706c794c6f6f70285f5f676c6f62616c206c6f6e67202a5f6b65726e656c5f636f6e746578742c205f5f636f6e7374616e74207563686172202a5f636f6e7374616e745f726567696f6e2c205f5f6c6f63616c207563686172202a5f6c6f63616c5f726567696f6e2c205f5f676c6f62616c20696e74202a5f61746f6d6963732c205f5f676c6f62616c207563686172202a412c205f5f676c6f62616c207563686172202a422c205f5f676c6f62616c207563686172202a43290a7b0a20206c6f6e67206c5f32392c206c5f32382c206c5f33382c206c5f32312c206c5f33372c206c5f32303b200a2020756c6f6e6720756c5f31372c20756c5f31382c20756c5f32352c20756c5f32342c20756c5f32322c20756c5f33352c20756c5f312c20756c5f322c20756c5f33342c20756c5f302c20756c5f33302c20756c5f372c20756c5f33392c20756c5f352c20756c5f363b200a2020696e7420695f32362c20695f32372c20695f31392c20695f392c20695f34312c20695f31302c20695f31312c20695f31322c20695f31332c20695f31342c20695f31362c20695f33332c20695f332c20695f342c20695f33362c20695f382c20695f34303b200a2020666c6f617420665f32332c20665f33322c20665f31352c20665f33313b200a0a20202f2f20424c4f434b20300a2020756c5f3020203d202028756c6f6e672920413b0a2020756c5f3120203d202028756c6f6e672920423b0a2020756c5f3220203d202028756c6f6e672920433b0a2020695f3320203d20206765745f676c6f62616c5f73697a652830293b0a2020695f3420203d20206765745f676c6f62616c5f73697a652831293b0a2020756c5f3520203d2020756c5f32202b2033324c3b0a2020756c5f3620203d2020756c5f31202b2033324c3b0a2020756c5f3720203d2020756c5f30202b2033324c3b0a2020695f3820203d20206765745f676c6f62616c5f69642830293b0a2020695f3920203d20206765745f676c6f62616c5f69642831293b0a20202f2f20424c4f434b2031204d4552474553205b302038205d0a2020695f313020203d2020695f393b0a2020666f72283b695f3130203c20313032343b290a20207b0a202020202f2f20424c4f434b20320a20202020695f313120203d2020695f3130203c3c2031303b0a20202020695f313220203d2020695f3131202b20363b0a202020202f2f20424c4f434b2033204d4552474553205b322037205d0a20202020695f313320203d2020695f383b0a20202020666f72283b695f3133203c20313032343b290a202020207b0a2020202020202f2f20424c4f434b20340a202020202020695f313420203d2020695f3133202b20363b0a2020202020202f2f20424c4f434b2035204d4552474553205b342036205d0a202020202020665f313520203d2020302e30463b0a202020202020695f313620203d2020303b0a202020202020666f72283b695f3136203c20313032343b290a2020202020207b0a20202020202020202f2f20424c4f434b20360a2020202020202020756c5f313720203d20202a28285f5f676c6f62616c20756c6f6e67202a2920756c5f37293b0a2020202020202020756c5f313820203d2020756c5f30202b20756c5f31373b0a2020202020202020695f313920203d2020695f3132202b20695f31363b0a20202020202020206c5f323020203d2020286c6f6e672920695f31393b0a20202020202020206c5f323120203d20206c5f3230203c3c20323b0a2020202020202020756c5f323220203d2020756c5f3138202b206c5f32313b0a2020202020202020665f323320203d20202a28285f5f676c6f62616c20666c6f6174202a2920756c5f3232293b0a2020202020202020756c5f323420203d20202a28285f5f676c6f62616c20756c6f6e67202a2920756c5f36293b0a2020202020202020756c5f323520203d2020756c5f31202b20756c5f32343b0a2020202020202020695f323620203d2020695f3136203c3c2031303b0a2020202020202020695f323720203d2020695f3236202b20695f31343b0a20202020202020206c5f323820203d2020286c6f6e672920695f32373b0a20202020202020206c5f323920203d20206c5f3238203c3c20323b0a2020202020202020756c5f333020203d2020756c5f3235202b206c5f32393b0a2020202020202020665f333120203d20202a28285f5f676c6f62616c20666c6f6174202a2920756c5f3330293b0a2020202020202020665f333220203d2020666d6128665f32332c20665f33312c20665f3135293b0a2020202020202020695f333320203d2020695f3136202b20313b0a2020202020202020665f313520203d2020665f33323b0a2020202020202020695f313620203d2020695f33333b0a2020202020207d20202f2f2042360a2020202020202f2f20424c4f434b20370a202020202020756c5f333420203d20202a28285f5f676c6f62616c20756c6f6e67202a2920756c5f35293b0a202020202020756c5f333520203d2020756c5f32202b20756c5f33343b0a202020202020695f333620203d2020695f3133202b20695f31323b0a2020202020206c5f333720203d2020286c6f6e672920695f33363b0a2020202020206c5f333820203d20206c5f3337203c3c20323b0a202020202020756c5f333920203d2020756c5f3335202b206c5f33383b0a2020202020202a28285f5f676c6f62616c20666c6f6174202a2920756c5f33392920203d2020665f31353b0a202020202020695f343020203d2020695f33202b20695f31333b0a202020202020695f313320203d2020695f34303b0a202020207d20202f2f2042370a202020202f2f20424c4f434b20380a20202020695f343120203d2020695f34202b20695f31303b0a20202020695f313020203d2020695f34313b0a20207d20202f2f2042380a20202f2f20424c4f434b20390a202072657475726e3b0a7d20202f2f20206b65726e656c0a  <||@
  HexCodeFile>>> <|@
end_nmethod
begin_compilation
  name " InvalidCompilationID"
  method "InvalidCompilationID"
  date 1743444014861
end_compilation
begin_compilation
  name " sketch-MultiplyKernel-1"
  method "sketch-MultiplyKernel-1"
  date 1743444014871
end_compilation
begin_compilation
  name " InvalidCompilationID"
  method "InvalidCompilationID"
  date 1743444014873
end_compilation
begin_compilation
  name " sketch-MultiplyKernel-1"
  method "sketch-MultiplyKernel-1"
  date 1743444014880
end_compilation
begin_compilation
  name " InvalidCompilationID"
  method "InvalidCompilationID"
  date 1743444014882
end_compilation
begin_compilation
  name " sketch-MultiplyKernel-1"
  method "sketch-MultiplyKernel-1"
  date 1743444014893
end_compilation
begin_cfg
  name "Final HIR schedule"
  begin_block
    name "B0"
    from_bci -1
    to_bci -1
    predecessors 
    successors "B1" 
    xhandlers
    flags 
    probability 4607182418800017408
    begin_IR
      HIR
f <@#|@fixed with next>@ <|@
tid v0 <|@
d <@d|@=== Debug Properties ===
hasSpeculationFence: false
stamp: void
=== Inputs ===
stateAfter: - 
=== Succesors ===
next: v8 
=== Usages ===
=== Predecessor ===
- >@ <|@
instruction <@StartNode|@org.graalvm.compiler.nodes.StartNode>@ stateAfter: - #next: v8  <|@  <|@
f <@~|@floating>@ <|@
tid f6 <|@
d <@d|@=== Debug Properties ===
isDefaultStable: false
nodeSourcePosition: at MatMul.MatMul.MultiplyKernel(MatMul.java:51) [bci: 18]
rawvalue: 0.0
stableDimension: 0
stamp: f32! [0.0]
stampKind: f32
value: float[0.0|0x0]
=== Inputs ===
=== Succesors ===
=== Usages ===
f10 
=== Predecessor ===
- >@ <|@
instruction <@Constant|@org.graalvm.compiler.nodes.ConstantNode>@  <|@  <|@
f <@~|@floating>@ <|@
tid i22 <|@
d <@d|@=== Debug Properties ===
isDefaultStable: false
nodeSourcePosition: at MatMul.MatMul.MultiplyKernel(MatMul.java:52) [bci: 54]
rawvalue: 1
stableDimension: 0
stamp: i32 [1]
stampKind: i32
value: int[1|0x1]
=== Inputs ===
=== Succesors ===
=== Usages ===
i23 i81 
=== Predecessor ===
- >@ <|@
instruction <@Constant|@org.graalvm.compiler.nodes.ConstantNode>@  <|@  <|@
f <@~|@floating>@ <|@
tid i81 <|@
d <@d|@=== Debug Properties ===
stamp: i32
=== Inputs ===
index: i22 
=== Succesors ===
=== Usages ===
i100 i32 
=== Predecessor ===
- >@ <|@
instruction <@LocalThreadId|@uk.ac.manchester.tornado.drivers.opencl.graal.nodes.LocalThreadIdNode>@ index: i22  <|@  <|@
f <@~|@floating>@ <|@
tid i66 <|@
d <@d|@=== Debug Properties ===
isDefaultStable: false
rawvalue: 6
stableDimension: 0
stamp: i32 [6]
stampKind: i32
value: int[6|0x6]
=== Inputs ===
=== Succesors ===
=== Usages ===
i33 i98 i100 
=== Predecessor ===
- >@ <|@
instruction <@Constant|@org.graalvm.compiler.nodes.ConstantNode>@  <|@  <|@
f <@~|@floating>@ <|@
tid i100 <|@
d <@d|@=== Debug Properties ===
stamp: i32
=== Inputs ===
x: i81 
y: i66 
=== Succesors ===
=== Usages ===
i101 
=== Predecessor ===
- >@ <|@
instruction <@+|@org.graalvm.compiler.nodes.calc.AddNode>@ x: i81 y: i66  <|@  <|@
f <@~|@floating>@ <|@
tid a3 <|@
d <@d|@=== Debug Properties ===
index: 2
stamp: a# uk.ac.manchester.tornado.api.types.matrix.Matrix2DFloat
uncheckedStamp: [null]
=== Inputs ===
=== Succesors ===
=== Usages ===
j76 v107 
=== Predecessor ===
- >@ <|@
instruction <@Parameter|@org.graalvm.compiler.nodes.ParameterNode>@  <|@  <|@
f <@~|@floating>@ <|@
tid j82 <|@
d <@d|@=== Debug Properties ===
isDefaultStable: false
nodeSourcePosition: at uk.ac.manchester.tornado.api.types.matrix.Matrix2DFloat.get(Matrix2DFloat.java:106) [bci: 1]
at MatMul.MatMul.MultiplyKernel(MatMul.java:54) [bci: 39]
rawvalue: 32
stableDimension: 0
stamp: i64 [32]
stampKind: i64
value: long[32|0x20]
=== Inputs ===
=== Succesors ===
=== Usages ===
v106 v107 v108 
=== Predecessor ===
- >@ <|@
instruction <@Constant|@org.graalvm.compiler.nodes.ConstantNode>@  <|@  <|@
f <@~|@floating>@ <|@
tid v107 <|@
d <@d|@=== Debug Properties ===
memoryRegister: uk.ac.manchester.tornado.drivers.opencl.graal.OCLArchitecture$OCLMemoryBase@73393584
stamp: void*
=== Inputs ===
base: a3 
index: j82 
=== Succesors ===
=== Usages ===
a87 
=== Predecessor ===
- >@ <|@
instruction <@OCLAddress|@uk.ac.manchester.tornado.drivers.opencl.graal.lir.OCLAddressNode>@ base: a3 index: j82  <|@  <|@
f <@~|@floating>@ <|@
tid i7 <|@
d <@d|@=== Debug Properties ===
isDefaultStable: false
nodeSourcePosition: at MatMul.MatMul.MultiplyKernel(MatMul.java:52) [bci: 21]
rawvalue: 0
stableDimension: 0
stamp: i32 [0]
stampKind: i32
value: int[0|0x0]
=== Inputs ===
=== Succesors ===
=== Usages ===
i11 i80 
=== Predecessor ===
- >@ <|@
instruction <@Constant|@org.graalvm.compiler.nodes.ConstantNode>@  <|@  <|@
f <@~|@floating>@ <|@
tid i80 <|@
d <@d|@=== Debug Properties ===
stamp: i32
=== Inputs ===
index: i7 
=== Succesors ===
=== Usages ===
i71 
=== Predecessor ===
- >@ <|@
instruction <@LocalThreadId|@uk.ac.manchester.tornado.drivers.opencl.graal.nodes.LocalThreadIdNode>@ index: i7  <|@  <|@
f <@~|@floating>@ <|@
tid i70 <|@
d <@d|@=== Debug Properties ===
isDefaultStable: false
nodeSourcePosition: at uk.ac.manchester.tornado.api.types.utils.StorageFormats.toRowMajor(StorageFormats.java:60) [bci: 2]
at uk.ac.manchester.tornado.api.types.matrix.Matrix2DFloat.set(Matrix2DFloat.java:110) [bci: 10]
at MatMul.MatMul.MultiplyKernel(MatMul.java:56) [bci: 67]
rawvalue: 10
stableDimension: 0
stamp: i32 [10]
stampKind: i32
value: int[10|0xa]
=== Inputs ===
=== Succesors ===
=== Usages ===
i71 i72 
=== Predecessor ===
- >@ <|@
instruction <@Constant|@org.graalvm.compiler.nodes.ConstantNode>@  <|@  <|@
f <@~|@floating>@ <|@
tid i71 <|@
d <@d|@=== Debug Properties ===
nodeSourcePosition: at uk.ac.manchester.tornado.api.types.utils.StorageFormats.toRowMajor(StorageFormats.java:60) [bci: 2]
at uk.ac.manchester.tornado.api.types.matrix.Matrix2DFloat.set(Matrix2DFloat.java:110) [bci: 10]
at MatMul.MatMul.MultiplyKernel(MatMul.java:56) [bci: 67]
stamp: i32 [-2147483648 - 2147482624] bits:x...x0000000000
=== Inputs ===
x: i80 
y: i70 
=== Succesors ===
=== Usages ===
i32 i98 
=== Predecessor ===
- >@ <|@
instruction <@<<|@org.graalvm.compiler.nodes.calc.LeftShiftNode>@ x: i80 y: i70  <|@  <|@
f <@~|@floating>@ <|@
tid i98 <|@
d <@d|@=== Debug Properties ===
stamp: i32 [-2147483642 - 2147482630] bits:x...x0000000110
=== Inputs ===
x: i71 
y: i66 
=== Succesors ===
=== Usages ===
i99 
=== Predecessor ===
- >@ <|@
instruction <@+|@org.graalvm.compiler.nodes.calc.AddNode>@ x: i71 y: i66  <|@  <|@
f <@~|@floating>@ <|@
tid i38 <|@
d <@d|@=== Debug Properties ===
isDefaultStable: false
nodeSourcePosition: at uk.ac.manchester.tornado.api.types.arrays.FloatArray.set(FloatArray.java:166) [bci: 15]
at uk.ac.manchester.tornado.api.types.matrix.Matrix2DFloat.set(Matrix2DFloat.java:110) [bci: 14]
at MatMul.MatMul.MultiplyKernel(MatMul.java:56) [bci: 67]
rawvalue: 2
stableDimension: 0
stamp: i32 [2]
stampKind: i32
value: int[2|0x2]
=== Inputs ===
=== Succesors ===
=== Usages ===
j39 j53 j65 
=== Predecessor ===
- >@ <|@
instruction <@Constant|@org.graalvm.compiler.nodes.ConstantNode>@  <|@  <|@
f <@~|@floating>@ <|@
tid a2 <|@
d <@d|@=== Debug Properties ===
index: 1
stamp: a# uk.ac.manchester.tornado.api.types.matrix.Matrix2DFloat
uncheckedStamp: [null]
=== Inputs ===
=== Succesors ===
=== Usages ===
j75 v106 
=== Predecessor ===
- >@ <|@
instruction <@Parameter|@org.graalvm.compiler.nodes.ParameterNode>@  <|@  <|@
f <@~|@floating>@ <|@
tid v106 <|@
d <@d|@=== Debug Properties ===
memoryRegister: uk.ac.manchester.tornado.drivers.opencl.graal.OCLArchitecture$OCLMemoryBase@73393584
stamp: void*
=== Inputs ===
base: a2 
index: j82 
=== Succesors ===
=== Usages ===
a84 
=== Predecessor ===
- >@ <|@
instruction <@OCLAddress|@uk.ac.manchester.tornado.drivers.opencl.graal.lir.OCLAddressNode>@ base: a2 index: j82  <|@  <|@
f <@~|@floating>@ <|@
tid i13 <|@
d <@d|@=== Debug Properties ===
isDefaultStable: false
nodeSourcePosition: at MatMul.MatMul.MultiplyKernel(MatMul.java:52) [bci: 26]
rawvalue: 1024
stableDimension: 0
stamp: i32 [1024]
stampKind: i32
value: int[1024|0x400]
=== Inputs ===
=== Succesors ===
=== Usages ===
v14 
=== Predecessor ===
- >@ <|@
instruction <@Constant|@org.graalvm.compiler.nodes.ConstantNode>@  <|@  <|@
f <@*|@fixed>@ <|@
tid v8 <|@
d <@d|@=== Debug Properties ===
nodeSourcePosition: at MatMul.MatMul.MultiplyKernel(MatMul.java:52) [bci: 24]
stamp: void
=== Inputs ===
=== Succesors ===
=== Usages ===
v9 
=== Predecessor ===
v0 >@ <|@
instruction <@EndNode|@org.graalvm.compiler.nodes.EndNode>@  <|@  <|@
    end_IR
  end_block
  begin_block
    name "B1"
    from_bci -1
    to_bci -1
    predecessors "B0" "B2" 
    successors "B2" "B3" 
    xhandlers
    flags "llh" 
    loop_index 0
    loop_depth 1
    probability 4611686018427387904
    begin_IR
      HIR
f <@~|@floating>@ <|@
tid f10 <|@
d <@d|@=== Debug Properties ===
nodeSourcePosition: at MatMul.MatMul.MultiplyKernel(MatMul.java:52) [bci: 24]
stamp: f32
valueDescription: f32
=== Inputs ===
merge: v9 
values: f6 f109 
=== Succesors ===
=== Usages ===
f109 v92 
=== Predecessor ===
- >@ <|@
instruction <@ValuePhi|@org.graalvm.compiler.nodes.ValuePhiNode>@ merge: v9 values: f6 f109  <|@  <|@
f <@~|@floating>@ <|@
tid i11 <|@
d <@d|@=== Debug Properties ===
nodeSourcePosition: at MatMul.MatMul.MultiplyKernel(MatMul.java:52) [bci: 24]
stamp: i32
valueDescription: i32
=== Inputs ===
merge: v9 
values: i7 i23 
=== Succesors ===
=== Usages ===
i72 v14 i23 i99 
=== Predecessor ===
- >@ <|@
instruction <@ValuePhi|@org.graalvm.compiler.nodes.ValuePhiNode>@ merge: v9 values: i7 i23  <|@  <|@
f <@#|@fixed with next>@ <|@
tid v9 <|@
d <@d|@=== Debug Properties ===
canEndsGuestSafepoint: true
canEndsSafepoint: true
canNeverOverflow: false
compilerInverted: false
disableCounted: false
hasSpeculationFence: false
loopOrigFrequency: 1.0
loopType: SIMPLE_LOOP
nextEndIndex: 1
nodeSourcePosition: at MatMul.MatMul.MultiplyKernel(MatMul.java:52) [bci: 24]
osrLoop: false
peelings: 0
rotated: false
splits: 0
stamp: void
stripMinedInner: false
stripMinedLimit: -1
stripMinedOuter: false
unrollFactor: 1
unswitches: 0
=== Inputs ===
stateAfter: - 
protectedNonOverflowingUnsigned: - 
overflowGuard: - 
interIterationAliasingGuard: - 
ends: v8 
=== Succesors ===
next: v19 
=== Usages ===
f10 i11 v15 v24 
=== Predecessor ===
- >@ <|@
instruction <@LoopBegin|@org.graalvm.compiler.nodes.LoopBeginNode>@ stateAfter: - protectedNonOverflowingUnsigned: - overflowGuard: - interIterationAliasingGuard: - ends: v8 #next: v19  <|@  <|@
f <@~|@floating>@ <|@
tid v14 <|@
d <@d|@=== Debug Properties ===
condition: LT
nodeSourcePosition: at MatMul.MatMul.MultiplyKernel(MatMul.java:52) [bci: 29]
op: org.graalvm.compiler.nodes.calc.IntegerLessThanNode$LessThanOp@33dc3b9e
stamp: void
unorderedIsTrue: false
=== Inputs ===
x: i11 
y: i13 
=== Succesors ===
=== Usages ===
v19 
=== Predecessor ===
- >@ <|@
instruction <@<|@org.graalvm.compiler.nodes.calc.IntegerLessThanNode>@ x: i11 y: i13  <|@  <|@
f <@*|@fixed>@ <|@
tid v19 <|@
d <@d|@=== Debug Properties ===
nodeSourcePosition: at MatMul.MatMul.MultiplyKernel(MatMul.java:52) [bci: 29]
profileData: UNKNOWN designatedSuccessorProbability: 0.5
stamp: void
=== Inputs ===
condition: v14 
=== Succesors ===
trueSuccessor: v18 
falseSuccessor: v15 
=== Usages ===
=== Predecessor ===
v9 >@ <|@
instruction <@If|@org.graalvm.compiler.nodes.IfNode>@ condition: v14 #trueSuccessor: v18 #falseSuccessor: v15  <|@  <|@
    end_IR
  end_block
  begin_block
    name "B2"
    from_bci -1
    to_bci -1
    predecessors "B1" 
    successors "B1" 
    xhandlers
    flags "lle" 
    loop_index 0
    loop_depth 1
    probability 4607182418800017408
    begin_IR
      HIR
f <@#|@fixed with next>@ <|@
tid v18 <|@
d <@d|@=== Debug Properties ===
hasSpeculationFence: false
nodeSourcePosition: at MatMul.MatMul.MultiplyKernel(MatMul.java:54) [bci: 32]
stamp: void
=== Inputs ===
=== Succesors ===
next: a84 
=== Usages ===
=== Predecessor ===
v19 >@ <|@
instruction <@Begin|@org.graalvm.compiler.nodes.BeginNode>@ #next: a84  <|@  <|@
f <@#|@fixed with next>@ <|@
tid a84 <|@
d <@d|@=== Debug Properties ===
accessStamp: a# uk.ac.manchester.tornado.api.types.arrays.FloatArray
barrierType: NONE
deoptReasonAndAction: [null]
deoptSpeculation: [null]
extendKind: DEFAULT
forceFixed: false
location: Matrix2DFloat.storage
memoryOrder: [null]
nodeSourcePosition: at uk.ac.manchester.tornado.api.types.matrix.Matrix2DFloat.get(Matrix2DFloat.java:106) [bci: 1]
at MatMul.MatMul.MultiplyKernel(MatMul.java:54) [bci: 39]
stamp: a# uk.ac.manchester.tornado.api.types.arrays.FloatArray
usedAsNullCheck: false
=== Inputs ===
stateBefore: - 
guard: - 
address: v106 
lastLocationAccess: - 
=== Succesors ===
next: f85 
=== Usages ===
j75 
=== Predecessor ===
v18 >@ <|@
instruction <@Read|@org.graalvm.compiler.nodes.memory.ReadNode>@ stateBefore: - guard: - address: v106 lastLocationAccess: - #next: f85  <|@  <|@
f <@~|@floating>@ <|@
tid j75 <|@
d <@d|@=== Debug Properties ===
stamp: i64
=== Inputs ===
base: a2 
offset: a84 
=== Succesors ===
=== Usages ===
v104 
=== Predecessor ===
- >@ <|@
instruction <@TornadoAddressArithmetic|@uk.ac.manchester.tornado.runtime.graal.nodes.calc.TornadoAddressArithmeticNode>@ base: a2 offset: a84  <|@  <|@
f <@~|@floating>@ <|@
tid i99 <|@
d <@d|@=== Debug Properties ===
stamp: i32
=== Inputs ===
x: i11 
y: i98 
=== Succesors ===
=== Usages ===
j50 
=== Predecessor ===
- >@ <|@
instruction <@+|@org.graalvm.compiler.nodes.calc.AddNode>@ x: i11 y: i98  <|@  <|@
f <@~|@floating>@ <|@
tid j50 <|@
d <@d|@=== Debug Properties ===
inputBits: 32
nodeSourcePosition: at uk.ac.manchester.tornado.api.types.arrays.FloatArray.get(FloatArray.java:177) [bci: 13]
at uk.ac.manchester.tornado.api.types.matrix.Matrix2DFloat.get(Matrix2DFloat.java:106) [bci: 13]
at MatMul.MatMul.MultiplyKernel(MatMul.java:54) [bci: 39]
resultBits: 64
stamp: i64 [-2147483648 - 2147483647]
=== Inputs ===
value: i99 
=== Succesors ===
=== Usages ===
j53 
=== Predecessor ===
- >@ <|@
instruction <@SignExtend|@org.graalvm.compiler.nodes.calc.SignExtendNode>@ value: i99  <|@  <|@
f <@~|@floating>@ <|@
tid j53 <|@
d <@d|@=== Debug Properties ===
nodeSourcePosition: at uk.ac.manchester.tornado.api.types.arrays.FloatArray.get(FloatArray.java:177) [bci: 14]
at uk.ac.manchester.tornado.api.types.matrix.Matrix2DFloat.get(Matrix2DFloat.java:106) [bci: 13]
at MatMul.MatMul.MultiplyKernel(MatMul.java:54) [bci: 39]
stamp: i64 [-8589934592 - 8589934588] bits:x...x00
=== Inputs ===
x: j50 
y: i38 
=== Succesors ===
=== Usages ===
v104 
=== Predecessor ===
- >@ <|@
instruction <@<<|@org.graalvm.compiler.nodes.calc.LeftShiftNode>@ x: j50 y: i38  <|@  <|@
f <@~|@floating>@ <|@
tid v104 <|@
d <@d|@=== Debug Properties ===
memoryRegister: uk.ac.manchester.tornado.drivers.opencl.graal.OCLArchitecture$OCLMemoryBase@73393584
stamp: void*
=== Inputs ===
base: j75 
index: j53 
=== Succesors ===
=== Usages ===
f85 
=== Predecessor ===
- >@ <|@
instruction <@OCLAddress|@uk.ac.manchester.tornado.drivers.opencl.graal.lir.OCLAddressNode>@ base: j75 index: j53  <|@  <|@
f <@#|@fixed with next>@ <|@
tid f85 <|@
d <@d|@=== Debug Properties ===
accessStamp: f32
barrierType: NONE
deoptReasonAndAction: [null]
deoptSpeculation: [null]
extendKind: DEFAULT
forceFixed: true
location: ANY_LOCATION
memoryOrder: PLAIN
nodeSourcePosition: at uk.ac.manchester.tornado.api.types.arrays.FloatArray.get(FloatArray.java:177) [bci: 14]
at uk.ac.manchester.tornado.api.types.matrix.Matrix2DFloat.get(Matrix2DFloat.java:106) [bci: 13]
at MatMul.MatMul.MultiplyKernel(MatMul.java:54) [bci: 39]
stamp: f32
usedAsNullCheck: false
=== Inputs ===
stateBefore: - 
guard: - 
address: v104 
lastLocationAccess: - 
=== Succesors ===
next: a87 
=== Usages ===
f109 
=== Predecessor ===
a84 >@ <|@
instruction <@Read|@org.graalvm.compiler.nodes.memory.ReadNode>@ stateBefore: - guard: - address: v104 lastLocationAccess: - #next: a87  <|@  <|@
f <@#|@fixed with next>@ <|@
tid a87 <|@
d <@d|@=== Debug Properties ===
accessStamp: a# uk.ac.manchester.tornado.api.types.arrays.FloatArray
barrierType: NONE
deoptReasonAndAction: [null]
deoptSpeculation: [null]
extendKind: DEFAULT
forceFixed: false
location: Matrix2DFloat.storage
memoryOrder: [null]
nodeSourcePosition: at uk.ac.manchester.tornado.api.types.matrix.Matrix2DFloat.get(Matrix2DFloat.java:106) [bci: 1]
at MatMul.MatMul.MultiplyKernel(MatMul.java:54) [bci: 47]
stamp: a# uk.ac.manchester.tornado.api.types.arrays.FloatArray
usedAsNullCheck: false
=== Inputs ===
stateBefore: - 
guard: - 
address: v107 
lastLocationAccess: - 
=== Succesors ===
next: f88 
=== Usages ===
j76 
=== Predecessor ===
f85 >@ <|@
instruction <@Read|@org.graalvm.compiler.nodes.memory.ReadNode>@ stateBefore: - guard: - address: v107 lastLocationAccess: - #next: f88  <|@  <|@
f <@~|@floating>@ <|@
tid j76 <|@
d <@d|@=== Debug Properties ===
stamp: i64
=== Inputs ===
base: a3 
offset: a87 
=== Succesors ===
=== Usages ===
v105 
=== Predecessor ===
- >@ <|@
instruction <@TornadoAddressArithmetic|@uk.ac.manchester.tornado.runtime.graal.nodes.calc.TornadoAddressArithmeticNode>@ base: a3 offset: a87  <|@  <|@
f <@~|@floating>@ <|@
tid i72 <|@
d <@d|@=== Debug Properties ===
nodeSourcePosition: at uk.ac.manchester.tornado.api.types.utils.StorageFormats.toRowMajor(StorageFormats.java:60) [bci: 2]
at uk.ac.manchester.tornado.api.types.matrix.Matrix2DFloat.get(Matrix2DFloat.java:106) [bci: 10]
at MatMul.MatMul.MultiplyKernel(MatMul.java:54) [bci: 47]
stamp: i32 [-2147483648 - 2147482624] bits:x...x0000000000
=== Inputs ===
x: i11 
y: i70 
=== Succesors ===
=== Usages ===
i101 
=== Predecessor ===
- >@ <|@
instruction <@<<|@org.graalvm.compiler.nodes.calc.LeftShiftNode>@ x: i11 y: i70  <|@  <|@
f <@~|@floating>@ <|@
tid i101 <|@
d <@d|@=== Debug Properties ===
stamp: i32
=== Inputs ===
x: i72 
y: i100 
=== Succesors ===
=== Usages ===
j62 
=== Predecessor ===
- >@ <|@
instruction <@+|@org.graalvm.compiler.nodes.calc.AddNode>@ x: i72 y: i100  <|@  <|@
f <@~|@floating>@ <|@
tid j62 <|@
d <@d|@=== Debug Properties ===
inputBits: 32
nodeSourcePosition: at uk.ac.manchester.tornado.api.types.arrays.FloatArray.get(FloatArray.java:177) [bci: 13]
at uk.ac.manchester.tornado.api.types.matrix.Matrix2DFloat.get(Matrix2DFloat.java:106) [bci: 13]
at MatMul.MatMul.MultiplyKernel(MatMul.java:54) [bci: 47]
resultBits: 64
stamp: i64 [-2147483648 - 2147483647]
=== Inputs ===
value: i101 
=== Succesors ===
=== Usages ===
j65 
=== Predecessor ===
- >@ <|@
instruction <@SignExtend|@org.graalvm.compiler.nodes.calc.SignExtendNode>@ value: i101  <|@  <|@
f <@~|@floating>@ <|@
tid j65 <|@
d <@d|@=== Debug Properties ===
nodeSourcePosition: at uk.ac.manchester.tornado.api.types.arrays.FloatArray.get(FloatArray.java:177) [bci: 14]
at uk.ac.manchester.tornado.api.types.matrix.Matrix2DFloat.get(Matrix2DFloat.java:106) [bci: 13]
at MatMul.MatMul.MultiplyKernel(MatMul.java:54) [bci: 47]
stamp: i64 [-8589934592 - 8589934588] bits:x...x00
=== Inputs ===
x: j62 
y: i38 
=== Succesors ===
=== Usages ===
v105 
=== Predecessor ===
- >@ <|@
instruction <@<<|@org.graalvm.compiler.nodes.calc.LeftShiftNode>@ x: j62 y: i38  <|@  <|@
f <@~|@floating>@ <|@
tid v105 <|@
d <@d|@=== Debug Properties ===
memoryRegister: uk.ac.manchester.tornado.drivers.opencl.graal.OCLArchitecture$OCLMemoryBase@73393584
stamp: void*
=== Inputs ===
base: j76 
index: j65 
=== Succesors ===
=== Usages ===
f88 
=== Predecessor ===
- >@ <|@
instruction <@OCLAddress|@uk.ac.manchester.tornado.drivers.opencl.graal.lir.OCLAddressNode>@ base: j76 index: j65  <|@  <|@
f <@#|@fixed with next>@ <|@
tid f88 <|@
d <@d|@=== Debug Properties ===
accessStamp: f32
barrierType: NONE
deoptReasonAndAction: [null]
deoptSpeculation: [null]
extendKind: DEFAULT
forceFixed: true
location: ANY_LOCATION
memoryOrder: PLAIN
nodeSourcePosition: at uk.ac.manchester.tornado.api.types.arrays.FloatArray.get(FloatArray.java:177) [bci: 14]
at uk.ac.manchester.tornado.api.types.matrix.Matrix2DFloat.get(Matrix2DFloat.java:106) [bci: 13]
at MatMul.MatMul.MultiplyKernel(MatMul.java:54) [bci: 47]
stamp: f32
usedAsNullCheck: false
=== Inputs ===
stateBefore: - 
guard: - 
address: v105 
lastLocationAccess: - 
=== Succesors ===
next: v24 
=== Usages ===
f109 
=== Predecessor ===
a87 >@ <|@
instruction <@Read|@org.graalvm.compiler.nodes.memory.ReadNode>@ stateBefore: - guard: - address: v105 lastLocationAccess: - #next: v24  <|@  <|@
f <@~|@floating>@ <|@
tid f109 <|@
d <@d|@=== Debug Properties ===
stamp: f32
=== Inputs ===
x: f85 
y: f88 
z: f10 
=== Succesors ===
=== Usages ===
f10 
=== Predecessor ===
- >@ <|@
instruction <@OCL-FMA|@uk.ac.manchester.tornado.drivers.opencl.graal.nodes.OCLFMANode>@ x: f85 y: f88 z: f10  <|@  <|@
f <@~|@floating>@ <|@
tid i23 <|@
d <@d|@=== Debug Properties ===
nodeSourcePosition: at MatMul.MatMul.MultiplyKernel(MatMul.java:52) [bci: 54]
stamp: i32
=== Inputs ===
x: i11 
y: i22 
=== Succesors ===
=== Usages ===
i11 
=== Predecessor ===
- >@ <|@
instruction <@+|@org.graalvm.compiler.nodes.calc.AddNode>@ x: i11 y: i22  <|@  <|@
f <@*|@fixed>@ <|@
tid v24 <|@
d <@d|@=== Debug Properties ===
canGuestSafepoint: true
canSafepoint: true
endIndex: 0
nodeSourcePosition: at MatMul.MatMul.MultiplyKernel(MatMul.java:52) [bci: 24]
stamp: void
=== Inputs ===
loopBegin: v9 
=== Succesors ===
=== Usages ===
=== Predecessor ===
f88 >@ <|@
instruction <@LoopEnd|@org.graalvm.compiler.nodes.LoopEndNode>@ loopBegin: v9  <|@  <|@
    end_IR
  end_block
  begin_block
    name "B3"
    from_bci -1
    to_bci -1
    predecessors "B1" 
    successors 
    xhandlers
    flags 
    probability 4607182418800017408
    begin_IR
      HIR
f <@#|@fixed with next>@ <|@
tid v15 <|@
d <@d|@=== Debug Properties ===
hasSpeculationFence: false
nodeSourcePosition: at MatMul.MatMul.MultiplyKernel(MatMul.java:56) [bci: 60]
stamp: void
=== Inputs ===
stateAfter: - 
loopBegin: v9 
=== Succesors ===
next: a91 
=== Usages ===
=== Predecessor ===
v19 >@ <|@
instruction <@LoopExit|@org.graalvm.compiler.nodes.LoopExitNode>@ stateAfter: - loopBegin: v9 #next: a91  <|@  <|@
f <@~|@floating>@ <|@
tid a4 <|@
d <@d|@=== Debug Properties ===
index: 3
stamp: a# uk.ac.manchester.tornado.api.types.matrix.Matrix2DFloat
uncheckedStamp: [null]
=== Inputs ===
=== Succesors ===
=== Usages ===
j77 v108 
=== Predecessor ===
- >@ <|@
instruction <@Parameter|@org.graalvm.compiler.nodes.ParameterNode>@  <|@  <|@
f <@~|@floating>@ <|@
tid v108 <|@
d <@d|@=== Debug Properties ===
memoryRegister: uk.ac.manchester.tornado.drivers.opencl.graal.OCLArchitecture$OCLMemoryBase@73393584
stamp: void*
=== Inputs ===
base: a4 
index: j82 
=== Succesors ===
=== Usages ===
a91 
=== Predecessor ===
- >@ <|@
instruction <@OCLAddress|@uk.ac.manchester.tornado.drivers.opencl.graal.lir.OCLAddressNode>@ base: a4 index: j82  <|@  <|@
f <@#|@fixed with next>@ <|@
tid a91 <|@
d <@d|@=== Debug Properties ===
accessStamp: a# uk.ac.manchester.tornado.api.types.arrays.FloatArray
barrierType: NONE
deoptReasonAndAction: [null]
deoptSpeculation: [null]
extendKind: DEFAULT
forceFixed: false
location: Matrix2DFloat.storage
memoryOrder: [null]
nodeSourcePosition: at uk.ac.manchester.tornado.api.types.matrix.Matrix2DFloat.set(Matrix2DFloat.java:110) [bci: 1]
at MatMul.MatMul.MultiplyKernel(MatMul.java:56) [bci: 67]
stamp: a# uk.ac.manchester.tornado.api.types.arrays.FloatArray
usedAsNullCheck: false
=== Inputs ===
stateBefore: - 
guard: - 
address: v108 
lastLocationAccess: - 
=== Succesors ===
next: v92 
=== Usages ===
j77 
=== Predecessor ===
v15 >@ <|@
instruction <@Read|@org.graalvm.compiler.nodes.memory.ReadNode>@ stateBefore: - guard: - address: v108 lastLocationAccess: - #next: v92  <|@  <|@
f <@~|@floating>@ <|@
tid j77 <|@
d <@d|@=== Debug Properties ===
stamp: i64
=== Inputs ===
base: a4 
offset: a91 
=== Succesors ===
=== Usages ===
v103 
=== Predecessor ===
- >@ <|@
instruction <@TornadoAddressArithmetic|@uk.ac.manchester.tornado.runtime.graal.nodes.calc.TornadoAddressArithmeticNode>@ base: a4 offset: a91  <|@  <|@
f <@~|@floating>@ <|@
tid i32 <|@
d <@d|@=== Debug Properties ===
nodeSourcePosition: at uk.ac.manchester.tornado.api.types.utils.StorageFormats.toRowMajor(StorageFormats.java:60) [bci: 4]
at uk.ac.manchester.tornado.api.types.matrix.Matrix2DFloat.set(Matrix2DFloat.java:110) [bci: 10]
at MatMul.MatMul.MultiplyKernel(MatMul.java:56) [bci: 67]
stamp: i32
=== Inputs ===
x: i71 
y: i81 
=== Succesors ===
=== Usages ===
i33 
=== Predecessor ===
- >@ <|@
instruction <@+|@org.graalvm.compiler.nodes.calc.AddNode>@ x: i71 y: i81  <|@  <|@
f <@~|@floating>@ <|@
tid i33 <|@
d <@d|@=== Debug Properties ===
nodeSourcePosition: at uk.ac.manchester.tornado.api.types.arrays.FloatArray.set(FloatArray.java:166) [bci: 12]
at uk.ac.manchester.tornado.api.types.matrix.Matrix2DFloat.set(Matrix2DFloat.java:110) [bci: 14]
at MatMul.MatMul.MultiplyKernel(MatMul.java:56) [bci: 67]
stamp: i32
=== Inputs ===
x: i32 
y: i66 
=== Succesors ===
=== Usages ===
j34 
=== Predecessor ===
- >@ <|@
instruction <@+|@org.graalvm.compiler.nodes.calc.AddNode>@ x: i32 y: i66  <|@  <|@
f <@~|@floating>@ <|@
tid j34 <|@
d <@d|@=== Debug Properties ===
inputBits: 32
nodeSourcePosition: at uk.ac.manchester.tornado.api.types.arrays.FloatArray.set(FloatArray.java:166) [bci: 13]
at uk.ac.manchester.tornado.api.types.matrix.Matrix2DFloat.set(Matrix2DFloat.java:110) [bci: 14]
at MatMul.MatMul.MultiplyKernel(MatMul.java:56) [bci: 67]
resultBits: 64
stamp: i64 [-2147483648 - 2147483647]
=== Inputs ===
value: i33 
=== Succesors ===
=== Usages ===
j39 
=== Predecessor ===
- >@ <|@
instruction <@SignExtend|@org.graalvm.compiler.nodes.calc.SignExtendNode>@ value: i33  <|@  <|@
f <@~|@floating>@ <|@
tid j39 <|@
d <@d|@=== Debug Properties ===
nodeSourcePosition: at uk.ac.manchester.tornado.api.types.arrays.FloatArray.set(FloatArray.java:166) [bci: 15]
at uk.ac.manchester.tornado.api.types.matrix.Matrix2DFloat.set(Matrix2DFloat.java:110) [bci: 14]
at MatMul.MatMul.MultiplyKernel(MatMul.java:56) [bci: 67]
stamp: i64 [-8589934592 - 8589934588] bits:x...x00
=== Inputs ===
x: j34 
y: i38 
=== Succesors ===
=== Usages ===
v103 
=== Predecessor ===
- >@ <|@
instruction <@<<|@org.graalvm.compiler.nodes.calc.LeftShiftNode>@ x: j34 y: i38  <|@  <|@
f <@~|@floating>@ <|@
tid v103 <|@
d <@d|@=== Debug Properties ===
memoryRegister: uk.ac.manchester.tornado.drivers.opencl.graal.OCLArchitecture$OCLMemoryBase@73393584
stamp: void*
=== Inputs ===
base: j77 
index: j39 
=== Succesors ===
=== Usages ===
v92 
=== Predecessor ===
- >@ <|@
instruction <@OCLAddress|@uk.ac.manchester.tornado.drivers.opencl.graal.lir.OCLAddressNode>@ base: j77 index: j39  <|@  <|@
f <@#|@fixed with next>@ <|@
tid v92 <|@
d <@d|@=== Debug Properties ===
barrierType: NONE
deoptReasonAndAction: [null]
deoptSpeculation: [null]
killedLocationIdentity: ANY_LOCATION
location: ANY_LOCATION
memoryOrder: PLAIN
nodeSourcePosition: at uk.ac.manchester.tornado.api.types.arrays.FloatArray.set(FloatArray.java:166) [bci: 15]
at uk.ac.manchester.tornado.api.types.matrix.Matrix2DFloat.set(Matrix2DFloat.java:110) [bci: 14]
at MatMul.MatMul.MultiplyKernel(MatMul.java:56) [bci: 67]
stamp: void
usedAsNullCheck: false
=== Inputs ===
stateBefore: - 
guard: - 
address: v103 
lastLocationAccess: - 
value: f10 
stateAfter: - 
=== Succesors ===
next: v25 
=== Usages ===
=== Predecessor ===
a91 >@ <|@
instruction <@Write|@org.graalvm.compiler.nodes.memory.WriteNode>@ stateBefore: - guard: - address: v103 lastLocationAccess: - value: f10 stateAfter: - #next: v25  <|@  <|@
f <@*|@fixed>@ <|@
tid v25 <|@
d <@d|@=== Debug Properties ===
nodeSourcePosition: at MatMul.MatMul.MultiplyKernel(MatMul.java:57) [bci: 70]
stamp: void
=== Inputs ===
memoryMap: - 
result: - 
=== Succesors ===
=== Usages ===
=== Predecessor ===
v92 >@ <|@
instruction <@Return|@org.graalvm.compiler.nodes.ReturnNode>@ memoryMap: - result: -  <|@  <|@
    end_IR
  end_block
end_cfg
begin_cfg
  name "After linear scan order"
  begin_block
    name "B0"
    from_bci -1
    to_bci -1
    predecessors 
    successors "B1" 
    xhandlers
    flags 
    probability 4607182418800017408
  end_block
  begin_block
    name "B1"
    from_bci -1
    to_bci -1
    predecessors "B0" "B2" 
    successors "B2" "B3" 
    xhandlers
    flags "llh" 
    loop_index 0
    loop_depth 1
    probability 4611686018427387904
  end_block
  begin_block
    name "B2"
    from_bci -1
    to_bci -1
    predecessors "B1" 
    successors "B1" 
    xhandlers
    flags "lle" 
    loop_index 0
    loop_depth 1
    probability 4607182418800017408
  end_block
  begin_block
    name "B3"
    from_bci -1
    to_bci -1
    predecessors "B1" 
    successors 
    xhandlers
    flags 
    probability 4607182418800017408
  end_block
end_cfg
begin_bytecodes
     0: aload_0       
     1: getfield      #3          // uk.ac.manchester.tornado.api.KernelContext.localIdx:java.lang.Integer
     4: invokevirtual #4          // java.lang.Integer.intValue:()int
     7: istore        4
     9: aload_0       
    10: getfield      #5          // uk.ac.manchester.tornado.api.KernelContext.localIdy:java.lang.Integer
    13: invokevirtual #4          // java.lang.Integer.intValue:()int
    16: istore        5
    18: fconst_0      
    19: fstore        6
    21: iconst_0      
    22: istore        7
    24: iload         7
    26: sipush        1024
    29: if_icmpge     60
    32: fload         6
    34: aload_1       
    35: iload         4
    37: iload         7
    39: invokevirtual #1          // uk.ac.manchester.tornado.api.types.matrix.Matrix2DFloat.get:(int, int)float
    42: aload_2       
    43: iload         7
    45: iload         5
    47: invokevirtual #1          // uk.ac.manchester.tornado.api.types.matrix.Matrix2DFloat.get:(int, int)float
    50: fmul          
    51: fadd          
    52: fstore        6
    54: iinc          
    57: goto          24
    60: aload_3       
    61: iload         4
    63: iload         5
    65: fload         6
    67: invokevirtual #2          // uk.ac.manchester.tornado.api.types.matrix.Matrix2DFloat.set:(int, int, float)void
    70: return        
   <|@
end_bytecodes
begin_cfg
  name "After OCLLIRGeneration"
  begin_block
    name "B0"
    from_bci -1
    to_bci -1
    predecessors 
    successors "B1" 
    xhandlers
    flags 
    probability 4607182418800017408
    begin_IR
      LIR
      nr   -1  <|@ instruction [] = LABEL alignment: 0 numbPhis: 0 label: ? <|@ <|@
      nr   -1  <|@ instruction v0|ULONG = ASSIGN (ulong) A <|@ <|@
      nr   -1  <|@ instruction v1|ULONG = ASSIGN (ulong) B <|@ <|@
      nr   -1  <|@ instruction v2|ULONG = ASSIGN (ulong) C <|@ <|@
      nr   -1  <|@ instruction v3|INT = ASSIGN get_local_id(int[1|0x1]) <|@ <|@
      nr   -1  <|@ instruction v4|INT = ASSIGN + v3|INT int[6|0x6] <|@ <|@
      nr   -1  <|@ instruction v5|ULONG = ASSIGN + v1|ULONG long[32|0x20] <|@ <|@
      nr   -1  <|@ instruction v6|INT = ASSIGN get_local_id(int[0|0x0]) <|@ <|@
      nr   -1  <|@ instruction v7|INT = ASSIGN << v6|INT int[10|0xa] <|@ <|@
      nr   -1  <|@ instruction v8|INT = ASSIGN + v7|INT int[6|0x6] <|@ <|@
      nr   -1  <|@ instruction v9|ULONG = ASSIGN + v0|ULONG long[32|0x20] <|@ <|@
    end_IR
  end_block
  begin_block
    name "B1"
    from_bci -1
    to_bci -1
    predecessors "B0" "B2" 
    successors "B2" "B3" 
    xhandlers
    flags "llh" 
    loop_index 0
    loop_depth 1
    probability 4611686018427387904
    begin_IR
      LIR
      nr   -1  <|@ instruction [] = LABEL alignment: 0 numbPhis: 0 label: ? <|@ <|@
      nr   -1  <|@ instruction v10|FLOAT = ASSIGN float[0.0|0x0] <|@ <|@
      nr   -1  <|@ instruction v11|INT = ASSIGN int[0|0x0] <|@ <|@
      nr   -1  <|@ instruction LOOPINIT <|@ <|@
      nr   -1  <|@ instruction LOOPPOST <|@ <|@
      nr   -1  <|@ instruction LOOPCONDITION < v11|INT int[1024|0x400] generateIfBreakStatement: true <|@ <|@
    end_IR
  end_block
  begin_block
    name "B2"
    from_bci -1
    to_bci -1
    predecessors "B1" 
    successors "B1" 
    xhandlers
    flags "lle" 
    loop_index 0
    loop_depth 1
    probability 4607182418800017408
    begin_IR
      LIR
      nr   -1  <|@ instruction [] = LABEL alignment: 0 numbPhis: 0 label: ? <|@ <|@
      nr   -1  <|@ instruction v12|ULONG = LOAD (cast: cast ptr null, address: v9|ULONG, index: null) <|@ <|@
      nr   -1  <|@ instruction v13|ULONG = ASSIGN + v0|ULONG v12|ULONG <|@ <|@
      nr   -1  <|@ instruction v14|INT = ASSIGN + v8|INT v11|INT <|@ <|@
      nr   -1  <|@ instruction v15|LONG = ASSIGN (long)  v14|INT <|@ <|@
      nr   -1  <|@ instruction v16|LONG = ASSIGN << v15|LONG int[2|0x2] <|@ <|@
      nr   -1  <|@ instruction v17|ULONG = ASSIGN + v13|ULONG v16|LONG <|@ <|@
      nr   -1  <|@ instruction v18|FLOAT = LOAD (cast: cast ptr null, address: v17|ULONG, index: null) <|@ <|@
      nr   -1  <|@ instruction v19|ULONG = LOAD (cast: cast ptr null, address: v5|ULONG, index: null) <|@ <|@
      nr   -1  <|@ instruction v20|ULONG = ASSIGN + v1|ULONG v19|ULONG <|@ <|@
      nr   -1  <|@ instruction v21|INT = ASSIGN << v11|INT int[10|0xa] <|@ <|@
      nr   -1  <|@ instruction v22|INT = ASSIGN + v21|INT v4|INT <|@ <|@
      nr   -1  <|@ instruction v23|LONG = ASSIGN (long)  v22|INT <|@ <|@
      nr   -1  <|@ instruction v24|LONG = ASSIGN << v23|LONG int[2|0x2] <|@ <|@
      nr   -1  <|@ instruction v25|ULONG = ASSIGN + v20|ULONG v24|LONG <|@ <|@
      nr   -1  <|@ instruction v26|FLOAT = LOAD (cast: cast ptr null, address: v25|ULONG, index: null) <|@ <|@
      nr   -1  <|@ instruction v27|FLOAT = ASSIGN fma v18|FLOAT v26|FLOAT v10|FLOAT <|@ <|@
      nr   -1  <|@ instruction v28|INT = ASSIGN + v11|INT int[1|0x1] <|@ <|@
      nr   -1  <|@ instruction v10|FLOAT = ASSIGN v27|FLOAT <|@ <|@
      nr   -1  <|@ instruction v11|INT = ASSIGN v28|INT <|@ <|@
    end_IR
  end_block
  begin_block
    name "B3"
    from_bci -1
    to_bci -1
    predecessors "B1" 
    successors 
    xhandlers
    flags 
    probability 4607182418800017408
    begin_IR
      LIR
      nr   -1  <|@ instruction [] = LABEL alignment: 0 numbPhis: 0 label: ? <|@ <|@
      nr   -1  <|@ instruction v29|ULONG = ASSIGN + v2|ULONG long[32|0x20] <|@ <|@
      nr   -1  <|@ instruction v30|ULONG = LOAD (cast: cast ptr null, address: v29|ULONG, index: null) <|@ <|@
      nr   -1  <|@ instruction v31|ULONG = ASSIGN + v2|ULONG v30|ULONG <|@ <|@
      nr   -1  <|@ instruction v32|INT = ASSIGN + v7|INT v3|INT <|@ <|@
      nr   -1  <|@ instruction v33|INT = ASSIGN + v32|INT int[6|0x6] <|@ <|@
      nr   -1  <|@ instruction v34|LONG = ASSIGN (long)  v33|INT <|@ <|@
      nr   -1  <|@ instruction v35|LONG = ASSIGN << v34|LONG int[2|0x2] <|@ <|@
      nr   -1  <|@ instruction v36|ULONG = ASSIGN + v31|ULONG v35|LONG <|@ <|@
      nr   -1  <|@ instruction STORE (rhs: v10|FLOAT, cast: cast ptr null, address: v36|ULONG, index: null) <|@ <|@
      nr   -1  <|@ instruction EXPR return <|@ <|@
    end_IR
  end_block
end_cfg
begin_bytecodes
     0: aload_0       
     1: getfield      #3          // uk.ac.manchester.tornado.api.KernelContext.localIdx:java.lang.Integer
     4: invokevirtual #4          // java.lang.Integer.intValue:()int
     7: istore        4
     9: aload_0       
    10: getfield      #5          // uk.ac.manchester.tornado.api.KernelContext.localIdy:java.lang.Integer
    13: invokevirtual #4          // java.lang.Integer.intValue:()int
    16: istore        5
    18: fconst_0      
    19: fstore        6
    21: iconst_0      
    22: istore        7
    24: iload         7
    26: sipush        1024
    29: if_icmpge     60
    32: fload         6
    34: aload_1       
    35: iload         4
    37: iload         7
    39: invokevirtual #1          // uk.ac.manchester.tornado.api.types.matrix.Matrix2DFloat.get:(int, int)float
    42: aload_2       
    43: iload         7
    45: iload         5
    47: invokevirtual #1          // uk.ac.manchester.tornado.api.types.matrix.Matrix2DFloat.get:(int, int)float
    50: fmul          
    51: fadd          
    52: fstore        6
    54: iinc          
    57: goto          24
    60: aload_3       
    61: iload         4
    63: iload         5
    65: fload         6
    67: invokevirtual #2          // uk.ac.manchester.tornado.api.types.matrix.Matrix2DFloat.set:(int, int, float)void
    70: return        
   <|@
end_bytecodes
begin_cfg
  name "After LIR generation"
  begin_block
    name "B0"
    from_bci -1
    to_bci -1
    predecessors 
    successors "B1" 
    xhandlers
    flags 
    probability 4607182418800017408
    begin_IR
      LIR
      nr   -1  <|@ instruction [] = LABEL alignment: 0 numbPhis: 0 label: ? <|@ <|@
      nr   -1  <|@ instruction v0|ULONG = ASSIGN (ulong) A <|@ <|@
      nr   -1  <|@ instruction v1|ULONG = ASSIGN (ulong) B <|@ <|@
      nr   -1  <|@ instruction v2|ULONG = ASSIGN (ulong) C <|@ <|@
      nr   -1  <|@ instruction v3|INT = ASSIGN get_local_id(int[1|0x1]) <|@ <|@
      nr   -1  <|@ instruction v4|INT = ASSIGN + v3|INT int[6|0x6] <|@ <|@
      nr   -1  <|@ instruction v5|ULONG = ASSIGN + v1|ULONG long[32|0x20] <|@ <|@
      nr   -1  <|@ instruction v6|INT = ASSIGN get_local_id(int[0|0x0]) <|@ <|@
      nr   -1  <|@ instruction v7|INT = ASSIGN << v6|INT int[10|0xa] <|@ <|@
      nr   -1  <|@ instruction v8|INT = ASSIGN + v7|INT int[6|0x6] <|@ <|@
      nr   -1  <|@ instruction v9|ULONG = ASSIGN + v0|ULONG long[32|0x20] <|@ <|@
    end_IR
  end_block
  begin_block
    name "B1"
    from_bci -1
    to_bci -1
    predecessors "B0" "B2" 
    successors "B2" "B3" 
    xhandlers
    flags "llh" 
    loop_index 0
    loop_depth 1
    probability 4611686018427387904
    begin_IR
      LIR
      nr   -1  <|@ instruction [] = LABEL alignment: 0 numbPhis: 0 label: ? <|@ <|@
      nr   -1  <|@ instruction v10|FLOAT = ASSIGN float[0.0|0x0] <|@ <|@
      nr   -1  <|@ instruction v11|INT = ASSIGN int[0|0x0] <|@ <|@
      nr   -1  <|@ instruction LOOPINIT <|@ <|@
      nr   -1  <|@ instruction LOOPPOST <|@ <|@
      nr   -1  <|@ instruction LOOPCONDITION < v11|INT int[1024|0x400] generateIfBreakStatement: true <|@ <|@
    end_IR
  end_block
  begin_block
    name "B2"
    from_bci -1
    to_bci -1
    predecessors "B1" 
    successors "B1" 
    xhandlers
    flags "lle" 
    loop_index 0
    loop_depth 1
    probability 4607182418800017408
    begin_IR
      LIR
      nr   -1  <|@ instruction [] = LABEL alignment: 0 numbPhis: 0 label: ? <|@ <|@
      nr   -1  <|@ instruction v12|ULONG = LOAD (cast: cast ptr null, address: v9|ULONG, index: null) <|@ <|@
      nr   -1  <|@ instruction v13|ULONG = ASSIGN + v0|ULONG v12|ULONG <|@ <|@
      nr   -1  <|@ instruction v14|INT = ASSIGN + v8|INT v11|INT <|@ <|@
      nr   -1  <|@ instruction v15|LONG = ASSIGN (long)  v14|INT <|@ <|@
      nr   -1  <|@ instruction v16|LONG = ASSIGN << v15|LONG int[2|0x2] <|@ <|@
      nr   -1  <|@ instruction v17|ULONG = ASSIGN + v13|ULONG v16|LONG <|@ <|@
      nr   -1  <|@ instruction v18|FLOAT = LOAD (cast: cast ptr null, address: v17|ULONG, index: null) <|@ <|@
      nr   -1  <|@ instruction v19|ULONG = LOAD (cast: cast ptr null, address: v5|ULONG, index: null) <|@ <|@
      nr   -1  <|@ instruction v20|ULONG = ASSIGN + v1|ULONG v19|ULONG <|@ <|@
      nr   -1  <|@ instruction v21|INT = ASSIGN << v11|INT int[10|0xa] <|@ <|@
      nr   -1  <|@ instruction v22|INT = ASSIGN + v21|INT v4|INT <|@ <|@
      nr   -1  <|@ instruction v23|LONG = ASSIGN (long)  v22|INT <|@ <|@
      nr   -1  <|@ instruction v24|LONG = ASSIGN << v23|LONG int[2|0x2] <|@ <|@
      nr   -1  <|@ instruction v25|ULONG = ASSIGN + v20|ULONG v24|LONG <|@ <|@
      nr   -1  <|@ instruction v26|FLOAT = LOAD (cast: cast ptr null, address: v25|ULONG, index: null) <|@ <|@
      nr   -1  <|@ instruction v27|FLOAT = ASSIGN fma v18|FLOAT v26|FLOAT v10|FLOAT <|@ <|@
      nr   -1  <|@ instruction v28|INT = ASSIGN + v11|INT int[1|0x1] <|@ <|@
      nr   -1  <|@ instruction v10|FLOAT = ASSIGN v27|FLOAT <|@ <|@
      nr   -1  <|@ instruction v11|INT = ASSIGN v28|INT <|@ <|@
    end_IR
  end_block
  begin_block
    name "B3"
    from_bci -1
    to_bci -1
    predecessors "B1" 
    successors 
    xhandlers
    flags 
    probability 4607182418800017408
    begin_IR
      LIR
      nr   -1  <|@ instruction [] = LABEL alignment: 0 numbPhis: 0 label: ? <|@ <|@
      nr   -1  <|@ instruction v29|ULONG = ASSIGN + v2|ULONG long[32|0x20] <|@ <|@
      nr   -1  <|@ instruction v30|ULONG = LOAD (cast: cast ptr null, address: v29|ULONG, index: null) <|@ <|@
      nr   -1  <|@ instruction v31|ULONG = ASSIGN + v2|ULONG v30|ULONG <|@ <|@
      nr   -1  <|@ instruction v32|INT = ASSIGN + v7|INT v3|INT <|@ <|@
      nr   -1  <|@ instruction v33|INT = ASSIGN + v32|INT int[6|0x6] <|@ <|@
      nr   -1  <|@ instruction v34|LONG = ASSIGN (long)  v33|INT <|@ <|@
      nr   -1  <|@ instruction v35|LONG = ASSIGN << v34|LONG int[2|0x2] <|@ <|@
      nr   -1  <|@ instruction v36|ULONG = ASSIGN + v31|ULONG v35|LONG <|@ <|@
      nr   -1  <|@ instruction STORE (rhs: v10|FLOAT, cast: cast ptr null, address: v36|ULONG, index: null) <|@ <|@
      nr   -1  <|@ instruction EXPR return <|@ <|@
    end_IR
  end_block
end_cfg
begin_bytecodes
     0: aload_0       
     1: getfield      #3          // uk.ac.manchester.tornado.api.KernelContext.localIdx:java.lang.Integer
     4: invokevirtual #4          // java.lang.Integer.intValue:()int
     7: istore        4
     9: aload_0       
    10: getfield      #5          // uk.ac.manchester.tornado.api.KernelContext.localIdy:java.lang.Integer
    13: invokevirtual #4          // java.lang.Integer.intValue:()int
    16: istore        5
    18: fconst_0      
    19: fstore        6
    21: iconst_0      
    22: istore        7
    24: iload         7
    26: sipush        1024
    29: if_icmpge     60
    32: fload         6
    34: aload_1       
    35: iload         4
    37: iload         7
    39: invokevirtual #1          // uk.ac.manchester.tornado.api.types.matrix.Matrix2DFloat.get:(int, int)float
    42: aload_2       
    43: iload         7
    45: iload         5
    47: invokevirtual #1          // uk.ac.manchester.tornado.api.types.matrix.Matrix2DFloat.get:(int, int)float
    50: fmul          
    51: fadd          
    52: fstore        6
    54: iinc          
    57: goto          24
    60: aload_3       
    61: iload         4
    63: iload         5
    65: fload         6
    67: invokevirtual #2          // uk.ac.manchester.tornado.api.types.matrix.Matrix2DFloat.set:(int, int, float)void
    70: return        
   <|@
end_bytecodes
begin_cfg
  name "After SaveCalleeSaveRegisters"
  begin_block
    name "B0"
    from_bci -1
    to_bci -1
    predecessors 
    successors "B1" 
    xhandlers
    flags 
    probability 4607182418800017408
    begin_IR
      LIR
      nr   -1  <|@ instruction [] = LABEL alignment: 0 numbPhis: 0 label: ? <|@ <|@
      nr   -1  <|@ instruction v0|ULONG = ASSIGN (ulong) A <|@ <|@
      nr   -1  <|@ instruction v1|ULONG = ASSIGN (ulong) B <|@ <|@
      nr   -1  <|@ instruction v2|ULONG = ASSIGN (ulong) C <|@ <|@
      nr   -1  <|@ instruction v3|INT = ASSIGN get_local_id(int[1|0x1]) <|@ <|@
      nr   -1  <|@ instruction v4|INT = ASSIGN + v3|INT int[6|0x6] <|@ <|@
      nr   -1  <|@ instruction v5|ULONG = ASSIGN + v1|ULONG long[32|0x20] <|@ <|@
      nr   -1  <|@ instruction v6|INT = ASSIGN get_local_id(int[0|0x0]) <|@ <|@
      nr   -1  <|@ instruction v7|INT = ASSIGN << v6|INT int[10|0xa] <|@ <|@
      nr   -1  <|@ instruction v8|INT = ASSIGN + v7|INT int[6|0x6] <|@ <|@
      nr   -1  <|@ instruction v9|ULONG = ASSIGN + v0|ULONG long[32|0x20] <|@ <|@
    end_IR
  end_block
  begin_block
    name "B1"
    from_bci -1
    to_bci -1
    predecessors "B0" "B2" 
    successors "B2" "B3" 
    xhandlers
    flags "llh" 
    loop_index 0
    loop_depth 1
    probability 4611686018427387904
    begin_IR
      LIR
      nr   -1  <|@ instruction [] = LABEL alignment: 0 numbPhis: 0 label: ? <|@ <|@
      nr   -1  <|@ instruction v10|FLOAT = ASSIGN float[0.0|0x0] <|@ <|@
      nr   -1  <|@ instruction v11|INT = ASSIGN int[0|0x0] <|@ <|@
      nr   -1  <|@ instruction LOOPINIT <|@ <|@
      nr   -1  <|@ instruction LOOPPOST <|@ <|@
      nr   -1  <|@ instruction LOOPCONDITION < v11|INT int[1024|0x400] generateIfBreakStatement: true <|@ <|@
    end_IR
  end_block
  begin_block
    name "B2"
    from_bci -1
    to_bci -1
    predecessors "B1" 
    successors "B1" 
    xhandlers
    flags "lle" 
    loop_index 0
    loop_depth 1
    probability 4607182418800017408
    begin_IR
      LIR
      nr   -1  <|@ instruction [] = LABEL alignment: 0 numbPhis: 0 label: ? <|@ <|@
      nr   -1  <|@ instruction v12|ULONG = LOAD (cast: cast ptr null, address: v9|ULONG, index: null) <|@ <|@
      nr   -1  <|@ instruction v13|ULONG = ASSIGN + v0|ULONG v12|ULONG <|@ <|@
      nr   -1  <|@ instruction v14|INT = ASSIGN + v8|INT v11|INT <|@ <|@
      nr   -1  <|@ instruction v15|LONG = ASSIGN (long)  v14|INT <|@ <|@
      nr   -1  <|@ instruction v16|LONG = ASSIGN << v15|LONG int[2|0x2] <|@ <|@
      nr   -1  <|@ instruction v17|ULONG = ASSIGN + v13|ULONG v16|LONG <|@ <|@
      nr   -1  <|@ instruction v18|FLOAT = LOAD (cast: cast ptr null, address: v17|ULONG, index: null) <|@ <|@
      nr   -1  <|@ instruction v19|ULONG = LOAD (cast: cast ptr null, address: v5|ULONG, index: null) <|@ <|@
      nr   -1  <|@ instruction v20|ULONG = ASSIGN + v1|ULONG v19|ULONG <|@ <|@
      nr   -1  <|@ instruction v21|INT = ASSIGN << v11|INT int[10|0xa] <|@ <|@
      nr   -1  <|@ instruction v22|INT = ASSIGN + v21|INT v4|INT <|@ <|@
      nr   -1  <|@ instruction v23|LONG = ASSIGN (long)  v22|INT <|@ <|@
      nr   -1  <|@ instruction v24|LONG = ASSIGN << v23|LONG int[2|0x2] <|@ <|@
      nr   -1  <|@ instruction v25|ULONG = ASSIGN + v20|ULONG v24|LONG <|@ <|@
      nr   -1  <|@ instruction v26|FLOAT = LOAD (cast: cast ptr null, address: v25|ULONG, index: null) <|@ <|@
      nr   -1  <|@ instruction v27|FLOAT = ASSIGN fma v18|FLOAT v26|FLOAT v10|FLOAT <|@ <|@
      nr   -1  <|@ instruction v28|INT = ASSIGN + v11|INT int[1|0x1] <|@ <|@
      nr   -1  <|@ instruction v10|FLOAT = ASSIGN v27|FLOAT <|@ <|@
      nr   -1  <|@ instruction v11|INT = ASSIGN v28|INT <|@ <|@
    end_IR
  end_block
  begin_block
    name "B3"
    from_bci -1
    to_bci -1
    predecessors "B1" 
    successors 
    xhandlers
    flags 
    probability 4607182418800017408
    begin_IR
      LIR
      nr   -1  <|@ instruction [] = LABEL alignment: 0 numbPhis: 0 label: ? <|@ <|@
      nr   -1  <|@ instruction v29|ULONG = ASSIGN + v2|ULONG long[32|0x20] <|@ <|@
      nr   -1  <|@ instruction v30|ULONG = LOAD (cast: cast ptr null, address: v29|ULONG, index: null) <|@ <|@
      nr   -1  <|@ instruction v31|ULONG = ASSIGN + v2|ULONG v30|ULONG <|@ <|@
      nr   -1  <|@ instruction v32|INT = ASSIGN + v7|INT v3|INT <|@ <|@
      nr   -1  <|@ instruction v33|INT = ASSIGN + v32|INT int[6|0x6] <|@ <|@
      nr   -1  <|@ instruction v34|LONG = ASSIGN (long)  v33|INT <|@ <|@
      nr   -1  <|@ instruction v35|LONG = ASSIGN << v34|LONG int[2|0x2] <|@ <|@
      nr   -1  <|@ instruction v36|ULONG = ASSIGN + v31|ULONG v35|LONG <|@ <|@
      nr   -1  <|@ instruction STORE (rhs: v10|FLOAT, cast: cast ptr null, address: v36|ULONG, index: null) <|@ <|@
      nr   -1  <|@ instruction EXPR return <|@ <|@
    end_IR
  end_block
end_cfg
begin_bytecodes
     0: aload_0       
     1: getfield      #3          // uk.ac.manchester.tornado.api.KernelContext.localIdx:java.lang.Integer
     4: invokevirtual #4          // java.lang.Integer.intValue:()int
     7: istore        4
     9: aload_0       
    10: getfield      #5          // uk.ac.manchester.tornado.api.KernelContext.localIdy:java.lang.Integer
    13: invokevirtual #4          // java.lang.Integer.intValue:()int
    16: istore        5
    18: fconst_0      
    19: fstore        6
    21: iconst_0      
    22: istore        7
    24: iload         7
    26: sipush        1024
    29: if_icmpge     60
    32: fload         6
    34: aload_1       
    35: iload         4
    37: iload         7
    39: invokevirtual #1          // uk.ac.manchester.tornado.api.types.matrix.Matrix2DFloat.get:(int, int)float
    42: aload_2       
    43: iload         7
    45: iload         5
    47: invokevirtual #1          // uk.ac.manchester.tornado.api.types.matrix.Matrix2DFloat.get:(int, int)float
    50: fmul          
    51: fadd          
    52: fstore        6
    54: iinc          
    57: goto          24
    60: aload_3       
    61: iload         4
    63: iload         5
    65: fload         6
    67: invokevirtual #2          // uk.ac.manchester.tornado.api.types.matrix.Matrix2DFloat.set:(int, int, float)void
    70: return        
   <|@
end_bytecodes
begin_cfg
  name "Before code generation"
  begin_block
    name "B0"
    from_bci -1
    to_bci -1
    predecessors 
    successors "B1" 
    xhandlers
    flags 
    probability 4607182418800017408
    begin_IR
      LIR
      nr   -1  <|@ instruction [] = LABEL alignment: 0 numbPhis: 0 label: ? <|@ <|@
      nr   -1  <|@ instruction v0|ULONG = ASSIGN (ulong) A <|@ <|@
      nr   -1  <|@ instruction v1|ULONG = ASSIGN (ulong) B <|@ <|@
      nr   -1  <|@ instruction v2|ULONG = ASSIGN (ulong) C <|@ <|@
      nr   -1  <|@ instruction v3|INT = ASSIGN get_local_id(int[1|0x1]) <|@ <|@
      nr   -1  <|@ instruction v4|INT = ASSIGN + v3|INT int[6|0x6] <|@ <|@
      nr   -1  <|@ instruction v5|ULONG = ASSIGN + v1|ULONG long[32|0x20] <|@ <|@
      nr   -1  <|@ instruction v6|INT = ASSIGN get_local_id(int[0|0x0]) <|@ <|@
      nr   -1  <|@ instruction v7|INT = ASSIGN << v6|INT int[10|0xa] <|@ <|@
      nr   -1  <|@ instruction v8|INT = ASSIGN + v7|INT int[6|0x6] <|@ <|@
      nr   -1  <|@ instruction v9|ULONG = ASSIGN + v0|ULONG long[32|0x20] <|@ <|@
    end_IR
  end_block
  begin_block
    name "B1"
    from_bci -1
    to_bci -1
    predecessors "B0" "B2" 
    successors "B2" "B3" 
    xhandlers
    flags "llh" 
    loop_index 0
    loop_depth 1
    probability 4611686018427387904
    begin_IR
      LIR
      nr   -1  <|@ instruction [] = LABEL alignment: 0 numbPhis: 0 label: ? <|@ <|@
      nr   -1  <|@ instruction v10|FLOAT = ASSIGN float[0.0|0x0] <|@ <|@
      nr   -1  <|@ instruction v11|INT = ASSIGN int[0|0x0] <|@ <|@
      nr   -1  <|@ instruction LOOPINIT <|@ <|@
      nr   -1  <|@ instruction LOOPPOST <|@ <|@
      nr   -1  <|@ instruction LOOPCONDITION < v11|INT int[1024|0x400] generateIfBreakStatement: true <|@ <|@
    end_IR
  end_block
  begin_block
    name "B2"
    from_bci -1
    to_bci -1
    predecessors "B1" 
    successors "B1" 
    xhandlers
    flags "lle" 
    loop_index 0
    loop_depth 1
    probability 4607182418800017408
    begin_IR
      LIR
      nr   -1  <|@ instruction [] = LABEL alignment: 0 numbPhis: 0 label: ? <|@ <|@
      nr   -1  <|@ instruction v12|ULONG = LOAD (cast: cast ptr null, address: v9|ULONG, index: null) <|@ <|@
      nr   -1  <|@ instruction v13|ULONG = ASSIGN + v0|ULONG v12|ULONG <|@ <|@
      nr   -1  <|@ instruction v14|INT = ASSIGN + v8|INT v11|INT <|@ <|@
      nr   -1  <|@ instruction v15|LONG = ASSIGN (long)  v14|INT <|@ <|@
      nr   -1  <|@ instruction v16|LONG = ASSIGN << v15|LONG int[2|0x2] <|@ <|@
      nr   -1  <|@ instruction v17|ULONG = ASSIGN + v13|ULONG v16|LONG <|@ <|@
      nr   -1  <|@ instruction v18|FLOAT = LOAD (cast: cast ptr null, address: v17|ULONG, index: null) <|@ <|@
      nr   -1  <|@ instruction v19|ULONG = LOAD (cast: cast ptr null, address: v5|ULONG, index: null) <|@ <|@
      nr   -1  <|@ instruction v20|ULONG = ASSIGN + v1|ULONG v19|ULONG <|@ <|@
      nr   -1  <|@ instruction v21|INT = ASSIGN << v11|INT int[10|0xa] <|@ <|@
      nr   -1  <|@ instruction v22|INT = ASSIGN + v21|INT v4|INT <|@ <|@
      nr   -1  <|@ instruction v23|LONG = ASSIGN (long)  v22|INT <|@ <|@
      nr   -1  <|@ instruction v24|LONG = ASSIGN << v23|LONG int[2|0x2] <|@ <|@
      nr   -1  <|@ instruction v25|ULONG = ASSIGN + v20|ULONG v24|LONG <|@ <|@
      nr   -1  <|@ instruction v26|FLOAT = LOAD (cast: cast ptr null, address: v25|ULONG, index: null) <|@ <|@
      nr   -1  <|@ instruction v27|FLOAT = ASSIGN fma v18|FLOAT v26|FLOAT v10|FLOAT <|@ <|@
      nr   -1  <|@ instruction v28|INT = ASSIGN + v11|INT int[1|0x1] <|@ <|@
      nr   -1  <|@ instruction v10|FLOAT = ASSIGN v27|FLOAT <|@ <|@
      nr   -1  <|@ instruction v11|INT = ASSIGN v28|INT <|@ <|@
    end_IR
  end_block
  begin_block
    name "B3"
    from_bci -1
    to_bci -1
    predecessors "B1" 
    successors 
    xhandlers
    flags 
    probability 4607182418800017408
    begin_IR
      LIR
      nr   -1  <|@ instruction [] = LABEL alignment: 0 numbPhis: 0 label: ? <|@ <|@
      nr   -1  <|@ instruction v29|ULONG = ASSIGN + v2|ULONG long[32|0x20] <|@ <|@
      nr   -1  <|@ instruction v30|ULONG = LOAD (cast: cast ptr null, address: v29|ULONG, index: null) <|@ <|@
      nr   -1  <|@ instruction v31|ULONG = ASSIGN + v2|ULONG v30|ULONG <|@ <|@
      nr   -1  <|@ instruction v32|INT = ASSIGN + v7|INT v3|INT <|@ <|@
      nr   -1  <|@ instruction v33|INT = ASSIGN + v32|INT int[6|0x6] <|@ <|@
      nr   -1  <|@ instruction v34|LONG = ASSIGN (long)  v33|INT <|@ <|@
      nr   -1  <|@ instruction v35|LONG = ASSIGN << v34|LONG int[2|0x2] <|@ <|@
      nr   -1  <|@ instruction v36|ULONG = ASSIGN + v31|ULONG v35|LONG <|@ <|@
      nr   -1  <|@ instruction STORE (rhs: v10|FLOAT, cast: cast ptr null, address: v36|ULONG, index: null) <|@ <|@
      nr   -1  <|@ instruction EXPR return <|@ <|@
    end_IR
  end_block
end_cfg
begin_bytecodes
     0: aload_0       
     1: getfield      #3          // uk.ac.manchester.tornado.api.KernelContext.localIdx:java.lang.Integer
     4: invokevirtual #4          // java.lang.Integer.intValue:()int
     7: istore        4
     9: aload_0       
    10: getfield      #5          // uk.ac.manchester.tornado.api.KernelContext.localIdy:java.lang.Integer
    13: invokevirtual #4          // java.lang.Integer.intValue:()int
    16: istore        5
    18: fconst_0      
    19: fstore        6
    21: iconst_0      
    22: istore        7
    24: iload         7
    26: sipush        1024
    29: if_icmpge     60
    32: fload         6
    34: aload_1       
    35: iload         4
    37: iload         7
    39: invokevirtual #1          // uk.ac.manchester.tornado.api.types.matrix.Matrix2DFloat.get:(int, int)float
    42: aload_2       
    43: iload         7
    45: iload         5
    47: invokevirtual #1          // uk.ac.manchester.tornado.api.types.matrix.Matrix2DFloat.get:(int, int)float
    50: fmul          
    51: fadd          
    52: fstore        6
    54: iinc          
    57: goto          24
    60: aload_3       
    61: iload         4
    63: iload         5
    65: fload         6
    67: invokevirtual #2          // uk.ac.manchester.tornado.api.types.matrix.Matrix2DFloat.set:(int, int, float)void
    70: return        
   <|@
end_bytecodes
begin_cfg
  name "After code generation"
end_cfg
begin_nmethod
  <<<HexCodeFile
  Platform Tornado OpenCL 64  <||@
  HexCode 0 23707261676d61204f50454e434c20455854454e53494f4e20636c5f6b68725f66703634203a20656e61626c6520200a23707261676d61204f50454e434c20455854454e53494f4e20636c5f6b68725f66703136203a20656e61626c6520200a23707261676d61204f50454e434c20455854454e53494f4e20636c5f6b68725f696e7436345f626173655f61746f6d696373203a20656e61626c6520200a5f5f6b65726e656c20766f6964204d756c7469706c794b65726e656c285f5f676c6f62616c206c6f6e67202a5f6b65726e656c5f636f6e746578742c205f5f636f6e7374616e74207563686172202a5f636f6e7374616e745f726567696f6e2c205f5f6c6f63616c207563686172202a5f6c6f63616c5f726567696f6e2c205f5f676c6f62616c20696e74202a5f61746f6d6963732c205f5f676c6f62616c207563686172202a412c205f5f676c6f62616c207563686172202a422c205f5f676c6f62616c207563686172202a43290a7b0a20206c6f6e67206c5f31352c206c5f33352c206c5f33342c206c5f31362c206c5f32332c206c5f32343b200a2020756c6f6e6720756c5f31392c20756c5f32302c20756c5f31372c20756c5f31332c20756c5f32352c20756c5f33362c20756c5f312c20756c5f322c20756c5f33312c20756c5f302c20756c5f32392c20756c5f33302c20756c5f31322c20756c5f392c20756c5f353b200a2020696e7420695f31312c20695f32382c20695f31342c20695f33322c20695f33332c20695f332c20695f342c20695f32312c20695f362c20695f32322c20695f372c20695f383b200a2020666c6f617420665f31302c20665f32362c20665f32372c20665f31383b200a0a20202f2f20424c4f434b20300a2020756c5f3020203d202028756c6f6e672920413b0a2020756c5f3120203d202028756c6f6e672920423b0a2020756c5f3220203d202028756c6f6e672920433b0a2020695f3320203d20206765745f6c6f63616c5f69642831293b0a2020695f3420203d2020695f33202b20363b0a2020756c5f3520203d2020756c5f31202b2033324c3b0a2020695f3620203d20206765745f6c6f63616c5f69642830293b0a2020695f3720203d2020695f36203c3c2031303b0a2020695f3820203d2020695f37202b20363b0a2020756c5f3920203d2020756c5f30202b2033324c3b0a20202f2f20424c4f434b2031204d4552474553205b302032205d0a2020665f313020203d2020302e30463b0a2020695f313120203d2020303b0a2020666f72283b695f3131203c20313032343b290a20207b0a202020202f2f20424c4f434b20320a20202020756c5f313220203d20202a28285f5f676c6f62616c20756c6f6e67202a2920756c5f39293b0a20202020756c5f313320203d2020756c5f30202b20756c5f31323b0a20202020695f313420203d2020695f38202b20695f31313b0a202020206c5f313520203d2020286c6f6e672920695f31343b0a202020206c5f313620203d20206c5f3135203c3c20323b0a20202020756c5f313720203d2020756c5f3133202b206c5f31363b0a20202020665f313820203d20202a28285f5f676c6f62616c20666c6f6174202a2920756c5f3137293b0a20202020756c5f313920203d20202a28285f5f676c6f62616c20756c6f6e67202a2920756c5f35293b0a20202020756c5f323020203d2020756c5f31202b20756c5f31393b0a20202020695f323120203d2020695f3131203c3c2031303b0a20202020695f323220203d2020695f3231202b20695f343b0a202020206c5f323320203d2020286c6f6e672920695f32323b0a202020206c5f323420203d20206c5f3233203c3c20323b0a20202020756c5f323520203d2020756c5f3230202b206c5f32343b0a20202020665f323620203d20202a28285f5f676c6f62616c20666c6f6174202a2920756c5f3235293b0a20202020665f323720203d2020666d6128665f31382c20665f32362c20665f3130293b0a20202020695f323820203d2020695f3131202b20313b0a20202020665f313020203d2020665f32373b0a20202020695f313120203d2020695f32383b0a20207d20202f2f2042320a20202f2f20424c4f434b20330a2020756c5f323920203d2020756c5f32202b2033324c3b0a2020756c5f333020203d20202a28285f5f676c6f62616c20756c6f6e67202a2920756c5f3239293b0a2020756c5f333120203d2020756c5f32202b20756c5f33303b0a2020695f333220203d2020695f37202b20695f333b0a2020695f333320203d2020695f3332202b20363b0a20206c5f333420203d2020286c6f6e672920695f33333b0a20206c5f333520203d20206c5f3334203c3c20323b0a2020756c5f333620203d2020756c5f3331202b206c5f33353b0a20202a28285f5f676c6f62616c20666c6f6174202a2920756c5f33362920203d2020665f31303b0a202072657475726e3b0a7d20202f2f20206b65726e656c0a  <||@
  HexCodeFile>>> <|@
end_nmethod
